{"type": "Feature", "id": 22306060, "properties": {"woe:id": 22306060, "woe:parent_id": 20113992, "woe:name": "Stazione di Cabiate", "woe:placetype": 20, "woe:placetype_name": "POI", "woe:lang": "ITA", "iso:country": "IT", "meta:provider": ["geoplanet:7.3.1", "geoplanet:7.3.2", "geoplanet:7.4.0", "geoplanet:7.4.1", "geoplanet:7.5.1", "geoplanet:7.5.2", "geoplanet:7.6.0", "geoplanet:7.8.1", "geoplanet:7.9.0", "geoplanet:7.10.0", "geoplanet:8.0.0", "woeplanet:8.0.0"], "meta:indexed": "2020-08-20T20:20:39.051260", "woe:alias_ITA_V": ["Stazione Cabiate", "Stazione Ferroviaria di Cabiate", "Stazione Ferroviaria Cabiate"], "meta:updated": "2020-08-22T02:30:24.262387", "woe:hierarchy": {"continent": 24865675, "country": 23424853, "town": 0, "planet": 1, "county": 12591808, "suburb": 0, "state": 7153338, "region": 0, "localadmin": 20076078}, "woe:timezone_id": 28350914, "woe:hash": "u0nebeh1614m", "woe:centroid": [9.16818, 45.67588], "geom:latitude": 45.67588, "geom:longitude": 9.16818, "geom:hash": "u0nebeh1614m", "woe:latitude": 45.67588, "geom:centroid": [9.16818, 45.67588], "woe:longitude": 9.16818, "woe:repo": "woeplanet-poi-it"}, "geometry": {"coordinates": [9.16818, 45.67588], "type": "Point"}}