{"type": "Feature", "id": 22625237, "geometry": {"type": "Point", "coordinates": [11.0986, 43.878799]}, "properties": {"woe:id": 22625237, "woe:parent_id": 15000195, "woe:name": "Castello Dell'imperatore", "woe:placetype": 20, "woe:placetype_name": "POI", "woe:lang": "ITA", "iso:country": "IT", "meta:provider": ["geoplanet:7.4.0", "geoplanet:7.4.1", "geoplanet:7.5.1", "geoplanet:7.5.2", "geoplanet:7.6.0", "geoplanet:7.8.1", "geoplanet:7.9.0", "geoplanet:7.10.0", "geoplanet:8.0.0", "woeplanet:8.0.0"], "meta:indexed": "2020-08-21T00:25:59.096003", "meta:updated": "2020-10-14T11:50:13.473424", "woe:hierarchy": {"continent": 24865675, "country": 23424853, "town": 0, "planet": 1, "county": 15022639, "suburb": 0, "state": 7153345, "region": 0, "localadmin": 12677565}, "woe:timezone_id": 28350914, "woe:hash": "spzcsecu80gz", "woe:centroid": [11.0986, 43.878799], "geom:latitude": 43.878799, "geom:longitude": 11.0986, "geom:hash": "spzcsecu80gz", "woe:latitude": 43.878799, "geom:centroid": [11.0986, 43.878799], "woe:longitude": 11.0986, "woe:repo": "woeplanet-poi-it", "geom:area": 0.0, "woe:scale": 19}}