{"type": "Feature", "id": 56056542, "geometry": {"type": "Point", "coordinates": [8.55722, 40.725159]}, "properties": {"woe:id": 56056542, "woe:parent_id": 723757, "woe:name": "Universit\u00e0 Degli Studi Di Sassari", "woe:placetype": 20, "woe:placetype_name": "POI", "woe:lang": "ITA", "iso:country": "IT", "meta:provider": ["geoplanet:7.3.1", "geoplanet:7.3.2", "geoplanet:7.4.0", "geoplanet:7.4.1", "geoplanet:7.5.1", "geoplanet:7.5.2", "geoplanet:7.6.0", "geoplanet:7.8.1", "geoplanet:7.9.0", "geoplanet:7.10.0", "geoplanet:8.0.0", "woeplanet:8.0.0"], "meta:indexed": "2020-08-20T20:20:40.712082", "meta:updated": "2020-10-14T11:50:14.327916", "woe:alias_ITA_S": ["Universita Degli Studi Di Sassari"], "woe:hierarchy": {"continent": 24865675, "country": 23424853, "town": 0, "planet": 1, "county": 12591861, "suburb": 0, "state": 7153343, "region": 0, "localadmin": 20076812}, "woe:timezone_id": 28350914, "woe:hash": "spnpdtz1jxvs", "woe:centroid": [8.55722, 40.725159], "geom:latitude": 40.725159, "geom:longitude": 8.55722, "geom:hash": "spnpdtz1jxvs", "woe:latitude": 40.725159, "geom:centroid": [8.55722, 40.725159], "woe:longitude": 8.55722, "woe:repo": "woeplanet-poi-it", "geom:area": 0.0, "woe:scale": 19}}