{"type": "Feature", "id": 22321022, "properties": {"woe:id": 22321022, "woe:parent_id": 725003, "woe:name": "Stazione di Merci Vanchiglia", "woe:placetype": 20, "woe:placetype_name": "POI", "woe:lang": "ITA", "iso:country": "IT", "meta:provider": ["geoplanet:7.3.1", "geoplanet:7.3.2", "geoplanet:7.4.0", "geoplanet:7.4.1", "geoplanet:7.5.1", "geoplanet:7.5.2", "geoplanet:7.6.0", "geoplanet:7.8.1", "geoplanet:7.9.0", "geoplanet:7.10.0", "geoplanet:8.0.0", "woeplanet:8.0.0"], "meta:indexed": "2020-08-20T20:20:39.513357", "woe:alias_ITA_V": ["Stazione Merci Vanchiglia", "Stazione Ferroviaria di Merci Vanchiglia", "Stazione Ferroviaria Merci Vanchiglia"], "meta:updated": "2020-08-22T02:30:24.499705", "woe:hierarchy": {"continent": 24865675, "country": 23424853, "town": 0, "planet": 1, "county": 12591807, "suburb": 0, "state": 7153341, "region": 0, "localadmin": 12675704}, "woe:timezone_id": 28350914, "woe:hash": "u0j2rq8nwb7j", "woe:centroid": [7.70171, 45.080769], "geom:latitude": 45.080769, "geom:longitude": 7.70171, "geom:hash": "u0j2rq8nwb7j", "woe:latitude": 45.080769, "geom:centroid": [7.70171, 45.080769], "woe:longitude": 7.70171, "woe:repo": "woeplanet-poi-it"}, "geometry": {"coordinates": [7.70171, 45.080769], "type": "Point"}}