{"type": "Feature", "id": 22604750, "properties": {"woe:id": 22604750, "woe:parent_id": 711080, "woe:name": "Universit\u00e0 degli Studi di Bologna", "woe:placetype": 20, "woe:placetype_name": "POI", "woe:lang": "ITA", "iso:country": "IT", "meta:provider": ["geoplanet:7.3.1", "geoplanet:7.3.2", "geoplanet:7.4.0", "geoplanet:7.4.1", "geoplanet:7.5.1", "geoplanet:7.5.2", "geoplanet:7.6.0", "geoplanet:7.8.1", "geoplanet:7.9.0", "geoplanet:7.10.0", "geoplanet:8.0.0", "woeplanet:8.0.0"], "meta:indexed": "2020-08-20T20:20:39.829888", "woe:alias_ITA_V": ["Universita Degli Studi", "Universit\u00e0 Degli Studi"], "meta:updated": "2020-08-22T02:30:24.622329", "woe:alias_ITA_S": ["Universita degli Studi di Bologna"], "woe:hierarchy": {"continent": 24865675, "country": 23424853, "town": 0, "planet": 1, "county": 12591871, "suburb": 0, "state": 7153334, "region": 0, "localadmin": 12676557}, "woe:timezone_id": 28350914, "woe:hash": "srbj4k6tdb33", "woe:centroid": [11.35243, 44.496948], "geom:latitude": 44.496948, "geom:longitude": 11.35243, "geom:hash": "srbj4k6tdb33", "woe:latitude": 44.496948, "geom:centroid": [11.35243, 44.496948], "woe:longitude": 11.35243, "woe:repo": "woeplanet-poi-it"}, "geometry": {"coordinates": [11.35243, 44.496948], "type": "Point"}}