{"type": "Feature", "id": 23096999, "properties": {"woe:id": 23096999, "woe:parent_id": 714158, "woe:name": "Stazione di Cittadella", "woe:placetype": 20, "woe:placetype_name": "POI", "woe:lang": "ITA", "iso:country": "IT", "meta:provider": ["geoplanet:7.3.1", "geoplanet:7.3.2", "geoplanet:7.4.0", "geoplanet:7.4.1", "geoplanet:7.5.1", "geoplanet:7.5.2", "geoplanet:7.6.0", "geoplanet:7.8.1", "geoplanet:7.9.0", "geoplanet:7.10.0", "geoplanet:8.0.0", "woeplanet:8.0.0"], "meta:indexed": "2020-08-20T20:20:40.230992", "woe:alias_ITA_V": ["Stazione Cittadella", "Stazione Ferroviaria di Cittadella", "Stazione Ferroviaria Cittadella"], "meta:updated": "2020-08-22T02:30:24.807974", "woe:hierarchy": {"continent": 24865675, "country": 23424853, "town": 0, "planet": 1, "county": 12591804, "suburb": 0, "state": 7153349, "region": 0, "localadmin": 20076700}, "woe:timezone_id": 28350914, "woe:hash": "u207sm0wnvdx", "woe:centroid": [11.78931, 45.643761], "geom:latitude": 45.643761, "geom:longitude": 11.78931, "geom:hash": "u207sm0wnvdx", "woe:latitude": 45.643761, "geom:centroid": [11.78931, 45.643761], "woe:longitude": 11.78931, "woe:repo": "woeplanet-poi-it"}, "geometry": {"coordinates": [11.78931, 45.643761], "type": "Point"}}