{"type": "Feature", "id": 22309339, "properties": {"woe:id": 22309339, "woe:parent_id": 726536, "woe:name": "Stazione di Dinegro", "woe:placetype": 20, "woe:placetype_name": "POI", "woe:lang": "ITA", "iso:country": "IT", "meta:provider": ["geoplanet:7.3.1", "geoplanet:7.3.2", "geoplanet:7.4.0", "geoplanet:7.4.1", "geoplanet:7.5.1", "geoplanet:7.5.2", "geoplanet:7.6.0", "geoplanet:7.8.1", "geoplanet:7.9.0", "geoplanet:7.10.0", "geoplanet:8.0.0", "woeplanet:8.0.0"], "meta:indexed": "2020-08-20T20:20:39.172973", "woe:alias_ITA_V": ["Stazione Dinegro"], "meta:updated": "2020-08-22T02:30:24.343297", "woe:hierarchy": {"continent": 24865675, "country": 23424853, "town": 0, "planet": 1, "county": 12591832, "suburb": 0, "state": 7153337, "region": 0, "localadmin": 12675811}, "woe:timezone_id": 28350914, "woe:hash": "spykdv33g6cq", "woe:centroid": [8.91177, 44.413921], "geom:latitude": 44.413921, "geom:longitude": 8.91177, "geom:hash": "spykdv33g6cq", "woe:latitude": 44.413921, "geom:centroid": [8.91177, 44.413921], "woe:longitude": 8.91177, "woe:repo": "woeplanet-poi-it"}, "geometry": {"coordinates": [8.91177, 44.413921], "type": "Point"}}