{"type": "Feature", "id": 22566087, "properties": {"woe:id": 22566087, "woe:parent_id": 29333998, "woe:name": "Stazione di Villa Pompea", "woe:placetype": 20, "woe:placetype_name": "POI", "woe:lang": "ITA", "iso:country": "IT", "meta:provider": ["geoplanet:7.3.1", "geoplanet:7.3.2", "geoplanet:7.4.0", "geoplanet:7.4.1", "geoplanet:7.5.1", "geoplanet:7.5.2", "geoplanet:7.6.0", "geoplanet:7.8.1", "geoplanet:7.9.0", "geoplanet:7.10.0", "geoplanet:8.0.0", "woeplanet:8.0.0"], "meta:indexed": "2020-08-20T20:20:39.637683", "woe:alias_ITA_V": ["Stazione Villa Pompea"], "meta:updated": "2020-08-22T02:30:24.547883", "woe:hierarchy": {"continent": 24865675, "country": 23424853, "town": 0, "planet": 1, "county": 12591813, "suburb": 0, "state": 7153338, "region": 0, "localadmin": 12679633}, "woe:timezone_id": 28350914, "woe:hash": "u0nej84e8yb3", "woe:centroid": [9.38579, 45.527981], "geom:latitude": 45.527981, "geom:longitude": 9.38579, "geom:hash": "u0nej84e8yb3", "woe:latitude": 45.527981, "geom:centroid": [9.38579, 45.527981], "woe:longitude": 9.38579, "woe:repo": "woeplanet-poi-it"}, "geometry": {"coordinates": [9.38579, 45.527981], "type": "Point"}}