{"type": "Feature", "id": 56056538, "geometry": {"type": "Point", "coordinates": [15.29763, 37.060989]}, "properties": {"woe:id": 56056538, "woe:parent_id": 724236, "woe:name": "Universit\u00e0 Di Architettura", "woe:placetype": 20, "woe:placetype_name": "POI", "woe:lang": "ITA", "iso:country": "IT", "meta:provider": ["geoplanet:7.3.1", "geoplanet:7.3.2", "geoplanet:7.4.0", "geoplanet:7.4.1", "geoplanet:7.5.1", "geoplanet:7.5.2", "geoplanet:7.6.0", "geoplanet:7.8.1", "geoplanet:7.9.0", "geoplanet:7.10.0", "geoplanet:8.0.0", "woeplanet:8.0.0"], "meta:indexed": "2020-08-20T20:20:40.708619", "meta:updated": "2020-10-14T11:50:14.323979", "woe:alias_ITA_S": ["Universita Di Architettura"], "woe:hierarchy": {"continent": 24865675, "country": 23424853, "town": 0, "planet": 1, "county": 12591894, "suburb": 0, "state": 7153344, "region": 0, "localadmin": 20077073}, "woe:timezone_id": 28350914, "woe:hash": "sqdfu4erut5d", "woe:centroid": [15.29763, 37.060989], "geom:latitude": 37.060989, "geom:longitude": 15.29763, "geom:hash": "sqdfu4erut5d", "woe:latitude": 37.060989, "geom:centroid": [15.29763, 37.060989], "woe:longitude": 15.29763, "woe:repo": "woeplanet-poi-it", "geom:area": 0.0, "woe:scale": 19}}