{"type": "Feature", "id": 23077231, "geometry": {"type": "Point", "coordinates": [9.89464, 45.602451]}, "properties": {"woe:id": 23077231, "woe:parent_id": 29334462, "woe:name": "Stazione di Palazzolo", "woe:placetype": 20, "woe:placetype_name": "POI", "woe:lang": "ITA", "iso:country": "IT", "meta:provider": ["geoplanet:7.3.1", "geoplanet:7.3.2", "geoplanet:7.4.0", "geoplanet:7.4.1", "geoplanet:7.5.1", "geoplanet:7.5.2", "geoplanet:7.6.0", "geoplanet:7.8.1", "geoplanet:7.9.0", "geoplanet:7.10.0", "geoplanet:8.0.0", "woeplanet:8.0.0"], "meta:indexed": "2020-08-20T20:20:40.180362", "woe:alias_ITA_V": ["Stazione Palazzolo Sull'oglio", "Stazione di Palazzolo Sull'oglio", "Stazione Ferroviaria Palazzolo Sull'oglio", "Stazione Ferroviaria di Palazzolo Sull'oglio", "Stazione Palazzolo", "Stazione Ferroviaria di Palazzolo", "Stazione Ferroviaria Palazzolo"], "meta:updated": "2020-10-14T11:50:13.061080", "woe:hierarchy": {"continent": 24865675, "country": 23424853, "town": 0, "planet": 1, "county": 12591840, "suburb": 0, "state": 7153338, "region": 0, "localadmin": 12680883}, "woe:timezone_id": 28350914, "woe:hash": "u0p53jtj9c42", "woe:centroid": [9.89464, 45.602451], "geom:latitude": 45.602451, "geom:longitude": 9.89464, "geom:hash": "u0p53jtj9c42", "woe:latitude": 45.602451, "geom:centroid": [9.89464, 45.602451], "woe:longitude": 9.89464, "woe:repo": "woeplanet-poi-it", "geom:area": 0.0, "woe:scale": 19}}