{"type": "Feature", "id": 23061361, "geometry": {"type": "Point", "coordinates": [8.95089, 44.416759]}, "properties": {"woe:id": 23061361, "woe:parent_id": 726538, "woe:name": "Stadio Luigi Ferraris", "woe:placetype": 20, "woe:placetype_name": "POI", "woe:lang": "ITA", "iso:country": "IT", "meta:provider": ["geoplanet:7.3.1", "geoplanet:7.3.2", "geoplanet:7.4.0", "geoplanet:7.4.1", "geoplanet:7.5.1", "geoplanet:7.5.2", "geoplanet:7.6.0", "geoplanet:7.8.1", "geoplanet:7.9.0", "geoplanet:7.10.0", "geoplanet:8.0.0", "woeplanet:8.0.0"], "meta:indexed": "2020-08-20T20:20:40.120348", "meta:updated": "2020-10-14T11:50:13.179986", "woe:hierarchy": {"continent": 24865675, "country": 23424853, "town": 0, "planet": 1, "county": 12591832, "suburb": 0, "state": 7153337, "region": 0, "localadmin": 12675811}, "woe:timezone_id": 28350914, "woe:hash": "spyketvf6ggr", "woe:centroid": [8.95089, 44.416759], "geom:latitude": 44.416759, "geom:longitude": 8.95089, "geom:hash": "spyketvf6ggr", "woe:latitude": 44.416759, "geom:centroid": [8.95089, 44.416759], "woe:longitude": 8.95089, "woe:repo": "woeplanet-poi-it", "geom:area": 0.0, "woe:scale": 19}}