{"type": "Feature", "id": 22553708, "geometry": {"type": "Point", "coordinates": [8.45953, 45.13401]}, "properties": {"woe:id": 22553708, "woe:parent_id": 712810, "woe:name": "Stazione di Casale Monferrato", "woe:placetype": 20, "woe:placetype_name": "POI", "woe:lang": "ITA", "iso:country": "IT", "meta:provider": ["geoplanet:7.3.1", "geoplanet:7.3.2", "geoplanet:7.4.0", "geoplanet:7.4.1", "geoplanet:7.5.1", "geoplanet:7.5.2", "geoplanet:7.6.0", "geoplanet:7.8.1", "geoplanet:7.9.0", "geoplanet:7.10.0", "geoplanet:8.0.0", "woeplanet:8.0.0"], "meta:indexed": "2020-08-20T20:20:39.604193", "woe:alias_ITA_V": ["Stazione Casale Monferrato", "Stazione Ferroviaria di Casale Monferrato", "Stazione Ferroviaria Casale Monferrato"], "meta:updated": "2020-10-14T11:50:13.332513", "woe:hierarchy": {"continent": 24865675, "country": 23424853, "town": 0, "planet": 1, "county": 12591853, "suburb": 0, "state": 7153341, "region": 0, "localadmin": 12677950}, "woe:timezone_id": 28350914, "woe:hash": "u0n0b82h9m6b", "woe:centroid": [8.45953, 45.13401], "geom:latitude": 45.13401, "geom:longitude": 8.45953, "geom:hash": "u0n0b82h9m6b", "woe:latitude": 45.13401, "geom:centroid": [8.45953, 45.13401], "woe:longitude": 8.45953, "woe:repo": "woeplanet-poi-it", "geom:area": 0.0, "woe:scale": 19}}