{"type": "Feature", "id": 23161016, "properties": {"woe:id": 23161016, "woe:parent_id": 718419, "woe:name": "Stazione di Misterbianco", "woe:placetype": 20, "woe:placetype_name": "POI", "woe:lang": "ITA", "iso:country": "IT", "meta:provider": ["geoplanet:7.3.1", "geoplanet:7.3.2", "geoplanet:7.4.0", "geoplanet:7.4.1", "geoplanet:7.5.1", "geoplanet:7.5.2", "geoplanet:7.6.0", "geoplanet:7.8.1", "geoplanet:7.9.0", "geoplanet:7.10.0", "geoplanet:8.0.0", "woeplanet:8.0.0"], "meta:indexed": "2020-08-20T20:20:40.497960", "woe:alias_ITA_V": ["Stazione Misterbianco", "Stazione Ferroviaria di Misterbianco", "Stazione Ferroviaria Misterbianco"], "meta:updated": "2020-08-22T02:30:24.936176", "woe:hierarchy": {"continent": 24865675, "country": 23424853, "town": 0, "planet": 1, "county": 12591830, "suburb": 0, "state": 7153344, "region": 0, "localadmin": 12680352}, "woe:timezone_id": 28350914, "woe:hash": "sqdtmwcyv5ty", "woe:centroid": [15.00995, 37.523609], "geom:latitude": 37.523609, "geom:longitude": 15.00995, "geom:hash": "sqdtmwcyv5ty", "woe:latitude": 37.523609, "geom:centroid": [15.00995, 37.523609], "woe:longitude": 15.00995, "woe:repo": "woeplanet-poi-it"}, "geometry": {"coordinates": [15.00995, 37.523609], "type": "Point"}}