{"type": "Feature", "id": 22609114, "geometry": {"type": "Point", "coordinates": [12.24177, 44.136662]}, "properties": {"woe:id": 22609114, "woe:parent_id": 713883, "woe:name": "Museo di Scienze Naturali", "woe:placetype": 20, "woe:placetype_name": "POI", "woe:lang": "ITA", "iso:country": "IT", "meta:provider": ["geoplanet:7.3.1", "geoplanet:7.3.2", "geoplanet:7.4.0", "geoplanet:7.4.1", "geoplanet:7.5.1", "geoplanet:7.5.2", "geoplanet:7.6.0", "geoplanet:7.8.1", "geoplanet:7.9.0", "geoplanet:7.10.0", "geoplanet:8.0.0", "woeplanet:8.0.0"], "meta:indexed": "2020-08-20T20:20:39.842199", "meta:updated": "2020-10-14T11:50:13.481790", "woe:hierarchy": {"continent": 24865675, "country": 23424853, "town": 0, "planet": 1, "county": 12591887, "suburb": 0, "state": 7153334, "region": 0, "localadmin": 12676908}, "woe:timezone_id": 28350914, "woe:hash": "srbendf4tyjk", "woe:centroid": [12.24177, 44.136662], "geom:latitude": 44.136662, "geom:longitude": 12.24177, "geom:hash": "srbendf4tyjk", "woe:latitude": 44.136662, "geom:centroid": [12.24177, 44.136662], "woe:longitude": 12.24177, "woe:repo": "woeplanet-poi-it", "geom:area": 0.0, "woe:scale": 19}}