{"type": "Feature", "id": 22310898, "properties": {"woe:id": 22310898, "woe:parent_id": 20111414, "woe:name": "Stazione di Sant'elena", "woe:placetype": 20, "woe:placetype_name": "POI", "woe:lang": "ITA", "iso:country": "IT", "meta:provider": ["geoplanet:7.3.2", "geoplanet:7.4.0", "geoplanet:7.4.1", "geoplanet:7.5.1", "geoplanet:7.5.2", "geoplanet:7.6.0", "geoplanet:7.8.1", "geoplanet:7.9.0", "geoplanet:7.10.0", "geoplanet:8.0.0", "woeplanet:8.0.0"], "meta:indexed": "2020-08-20T22:04:39.961080", "woe:alias_ITA_V": ["Stazione Ferroviaria Sant'elena Este", "Stazione Sant'elena Este", "Stazione Ferroviaria di Sant'elena Este", "Stazione di Sant'elena Este", "Stazione Sant'elena", "Stazione Ferroviaria di Sant'elena", "Stazione Ferroviaria Sant'elena"], "meta:updated": "2020-08-22T02:30:24.373695", "woe:hierarchy": {"continent": 24865675, "country": 23424853, "town": 0, "planet": 1, "county": 12591804, "suburb": 0, "state": 7153349, "region": 0, "localadmin": 12679164}, "woe:timezone_id": 28350914, "woe:hash": "u2034s2c352u", "woe:centroid": [11.7125, 45.19936], "geom:latitude": 45.19936, "geom:longitude": 11.7125, "geom:hash": "u2034s2c352u", "woe:latitude": 45.19936, "geom:centroid": [11.7125, 45.19936], "woe:longitude": 11.7125, "woe:repo": "woeplanet-poi-it"}, "geometry": {"coordinates": [11.7125, 45.19936], "type": "Point"}}