{"type": "Feature", "id": 56056406, "properties": {"woe:id": 56056406, "woe:parent_id": 725677, "woe:name": "Universit\u00e0 Degli Studi Insubria", "woe:placetype": 20, "woe:placetype_name": "POI", "woe:lang": "ITA", "iso:country": "IT", "meta:provider": ["geoplanet:7.3.1", "geoplanet:7.3.2", "geoplanet:7.4.0", "geoplanet:7.4.1", "geoplanet:7.5.1", "geoplanet:7.5.2", "geoplanet:7.6.0", "geoplanet:7.8.1", "geoplanet:7.9.0", "geoplanet:7.10.0", "geoplanet:8.0.0", "woeplanet:8.0.0"], "meta:indexed": "2020-08-20T20:20:40.611725", "meta:updated": "2020-08-22T02:30:24.967860", "woe:alias_ITA_S": ["Universita Degli Studi Insubria"], "woe:hierarchy": {"continent": 24865675, "country": 23424853, "town": 0, "planet": 1, "county": 12591884, "suburb": 0, "state": 7153338, "region": 0, "localadmin": 12677586}, "woe:timezone_id": 28350914, "woe:hash": "u0nk8uk2b20u", "woe:centroid": [8.82787, 45.814491], "geom:latitude": 45.814491, "geom:longitude": 8.82787, "geom:hash": "u0nk8uk2b20u", "woe:latitude": 45.814491, "geom:centroid": [8.82787, 45.814491], "woe:longitude": 8.82787, "woe:repo": "woeplanet-poi-it"}, "geometry": {"coordinates": [8.82787, 45.814491], "type": "Point"}}