{"type": "Feature", "id": 56056420, "geometry": {"type": "Point", "coordinates": [9.16417, 45.504028]}, "properties": {"woe:id": 56056420, "woe:parent_id": 711351, "woe:name": "Politecnico Di Milano/architettura", "woe:placetype": 20, "woe:placetype_name": "POI", "woe:lang": "ITA", "iso:country": "IT", "meta:provider": ["geoplanet:7.3.1", "geoplanet:7.3.2", "geoplanet:7.4.0", "geoplanet:7.4.1", "geoplanet:7.5.1", "geoplanet:7.5.2", "geoplanet:7.6.0", "geoplanet:7.8.1", "geoplanet:7.9.0", "geoplanet:7.10.0", "geoplanet:8.0.0", "woeplanet:8.0.0"], "meta:indexed": "2020-08-20T20:20:40.621324", "meta:updated": "2020-10-14T11:50:14.255186", "woe:hierarchy": {"continent": 24865675, "country": 23424853, "town": 0, "planet": 1, "county": 12591813, "suburb": 0, "state": 7153338, "region": 0, "localadmin": 12675801}, "woe:timezone_id": 28350914, "woe:hash": "u0ndbec0htsk", "woe:centroid": [9.16417, 45.504028], "geom:latitude": 45.504028, "geom:longitude": 9.16417, "geom:hash": "u0ndbec0htsk", "woe:latitude": 45.504028, "geom:centroid": [9.16417, 45.504028], "woe:longitude": 9.16417, "woe:repo": "woeplanet-poi-it", "geom:area": 0.0, "woe:scale": 19}}