{"type": "Feature", "id": 23115236, "geometry": {"type": "Point", "coordinates": [12.85889, 43.345619]}, "properties": {"woe:id": 23115236, "woe:parent_id": 717944, "woe:name": "Stazione di Melano Marischio", "woe:placetype": 20, "woe:placetype_name": "POI", "woe:lang": "ITA", "iso:country": "IT", "meta:provider": ["geoplanet:7.3.1", "geoplanet:7.3.2", "geoplanet:7.4.0", "geoplanet:7.4.1", "geoplanet:7.5.1", "geoplanet:7.5.2", "geoplanet:7.6.0", "geoplanet:7.8.1", "geoplanet:7.9.0", "geoplanet:7.10.0", "geoplanet:8.0.0", "woeplanet:8.0.0"], "meta:indexed": "2020-08-20T20:20:40.279445", "woe:alias_ITA_V": ["Stazione Ferroviaria di Melano-Marischio", "Stazione Ferroviaria Melano-Marischio", "Stazione di Melano-Marischio", "Stazione Melano-Marischio", "Stazione Melano Marischio", "Stazione Ferroviaria di Melano Marischio", "Stazione Ferroviaria Melano Marischio"], "meta:updated": "2020-10-14T11:50:14.511635", "woe:hierarchy": {"continent": 24865675, "country": 23424853, "town": 0, "planet": 1, "county": 12591847, "suburb": 0, "state": 7153339, "region": 0, "localadmin": 12675773}, "woe:timezone_id": 28350914, "woe:hash": "sr9nsdgd9c52", "woe:centroid": [12.85889, 43.345619], "geom:latitude": 43.345619, "geom:longitude": 12.85889, "geom:hash": "sr9nsdgd9c52", "woe:latitude": 43.345619, "geom:centroid": [12.85889, 43.345619], "woe:longitude": 12.85889, "woe:repo": "woeplanet-poi-it", "geom:area": 0.0, "woe:scale": 19}}