{"type": "Feature", "id": 56059405, "geometry": {"type": "Point", "coordinates": [13.71693, 43.161789]}, "properties": {"woe:id": 56059405, "woe:parent_id": 715393, "woe:name": "Conservatorio G.b. Pergolesi", "woe:placetype": 20, "woe:placetype_name": "POI", "woe:lang": "ITA", "iso:country": "IT", "meta:provider": ["geoplanet:7.3.1", "geoplanet:7.3.2", "geoplanet:7.4.0", "geoplanet:7.4.1", "geoplanet:7.5.1", "geoplanet:7.5.2", "geoplanet:7.6.0", "geoplanet:7.8.1", "geoplanet:7.9.0", "geoplanet:7.10.0", "geoplanet:8.0.0", "woeplanet:8.0.0"], "meta:indexed": "2020-08-20T20:20:40.740240", "meta:updated": "2020-10-14T11:50:14.292054", "woe:hierarchy": {"continent": 24865675, "country": 23424853, "town": 0, "planet": 1, "county": 56558470, "suburb": 0, "state": 7153339, "region": 0, "localadmin": 20076792}, "woe:timezone_id": 28350914, "woe:hash": "sr9v81k7essk", "woe:centroid": [13.71693, 43.161789], "geom:latitude": 43.161789, "geom:longitude": 13.71693, "geom:hash": "sr9v81k7essk", "woe:latitude": 43.161789, "geom:centroid": [13.71693, 43.161789], "woe:longitude": 13.71693, "woe:repo": "woeplanet-poi-it", "geom:area": 0.0, "woe:scale": 19}}