{"type": "Feature", "id": 22542162, "properties": {"woe:id": 22542162, "woe:parent_id": 713988, "woe:name": "Museo del Tessile", "woe:placetype": 20, "woe:placetype_name": "POI", "woe:lang": "ITA", "iso:country": "IT", "meta:provider": ["geoplanet:7.3.1", "geoplanet:7.3.2", "geoplanet:7.4.0", "geoplanet:7.4.1", "geoplanet:7.5.1", "geoplanet:7.5.2", "geoplanet:7.6.0", "geoplanet:7.8.1", "geoplanet:7.9.0", "geoplanet:7.10.0", "geoplanet:8.0.0", "woeplanet:8.0.0"], "meta:indexed": "2020-08-20T20:20:39.565057", "meta:updated": "2020-08-22T02:30:24.520200", "woe:hierarchy": {"continent": 24865675, "country": 23424853, "town": 0, "planet": 1, "county": 12591807, "suburb": 0, "state": 7153341, "region": 0, "localadmin": 12678607}, "woe:timezone_id": 28350914, "woe:hash": "u0j81czqepkp", "woe:centroid": [7.82137, 45.010769], "geom:latitude": 45.010769, "geom:longitude": 7.82137, "geom:hash": "u0j81czqepkp", "woe:latitude": 45.010769, "geom:centroid": [7.82137, 45.010769], "woe:longitude": 7.82137, "woe:repo": "woeplanet-poi-it"}, "geometry": {"coordinates": [7.82137, 45.010769], "type": "Point"}}