{"type": "Feature", "id": 23052154, "geometry": {"type": "Point", "coordinates": [7.6887, 45.064678]}, "properties": {"woe:id": 23052154, "woe:parent_id": 725003, "woe:name": "Museo Regionale di Scienze Naturali", "woe:placetype": 20, "woe:placetype_name": "POI", "woe:lang": "ITA", "iso:country": "IT", "meta:provider": ["geoplanet:7.3.1", "geoplanet:7.3.2", "geoplanet:7.4.0", "geoplanet:7.4.1", "geoplanet:7.5.1", "geoplanet:7.5.2", "geoplanet:7.6.0", "geoplanet:7.8.1", "geoplanet:7.9.0", "geoplanet:7.10.0", "geoplanet:8.0.0", "woeplanet:8.0.0"], "meta:indexed": "2020-08-20T20:20:40.066593", "meta:updated": "2020-10-14T11:50:13.170720", "woe:hierarchy": {"continent": 24865675, "country": 23424853, "town": 0, "planet": 1, "county": 12591807, "suburb": 0, "state": 7153341, "region": 0, "localadmin": 12675704}, "woe:timezone_id": 28350914, "woe:hash": "u0j2qgy8z8y7", "woe:centroid": [7.6887, 45.064678], "geom:latitude": 45.064678, "geom:longitude": 7.6887, "geom:hash": "u0j2qgy8z8y7", "woe:latitude": 45.064678, "geom:centroid": [7.6887, 45.064678], "woe:longitude": 7.6887, "woe:repo": "woeplanet-poi-it", "geom:area": 0.0, "woe:scale": 19}}