{"type": "Feature", "id": 23156411, "properties": {"woe:id": 23156411, "woe:parent_id": 12675770, "woe:name": "Capo Gallo", "woe:placetype": 20, "woe:placetype_name": "POI", "woe:lang": "ITA", "iso:country": "IT", "meta:provider": ["geoplanet:7.3.1", "geoplanet:7.3.2", "geoplanet:7.4.0", "geoplanet:7.4.1", "geoplanet:7.5.1", "geoplanet:7.5.2", "geoplanet:7.6.0", "geoplanet:7.8.1", "geoplanet:7.9.0", "geoplanet:7.10.0", "geoplanet:8.0.0", "woeplanet:8.0.0"], "meta:indexed": "2020-08-20T20:20:40.451254", "meta:updated": "2020-08-22T02:30:24.911889", "woe:hierarchy": {"continent": 24865675, "country": 23424853, "town": 0, "planet": 1, "county": 12591846, "suburb": 0, "state": 7153344, "region": 0, "localadmin": 12675770}, "woe:timezone_id": 28350914, "woe:hash": "sqc3rhqutc4g", "woe:centroid": [13.32495, 38.212601], "geom:latitude": 38.212601, "geom:longitude": 13.32495, "geom:hash": "sqc3rhqutc4g", "woe:latitude": 38.212601, "geom:centroid": [13.32495, 38.212601], "woe:longitude": 13.32495, "woe:repo": "woeplanet-poi-it"}, "geometry": {"coordinates": [13.32495, 38.212601], "type": "Point"}}