{"type": "Feature", "id": 22554394, "geometry": {"type": "Point", "coordinates": [8.86204, 44.89957]}, "properties": {"woe:id": 22554394, "woe:parent_id": 725154, "woe:name": "Stazione di Tortona", "woe:placetype": 20, "woe:placetype_name": "POI", "woe:lang": "ITA", "iso:country": "IT", "meta:provider": ["geoplanet:7.3.1", "geoplanet:7.3.2", "geoplanet:7.4.0", "geoplanet:7.4.1", "geoplanet:7.5.1", "geoplanet:7.5.2", "geoplanet:7.6.0", "geoplanet:7.8.1", "geoplanet:7.9.0", "geoplanet:7.10.0", "geoplanet:8.0.0", "woeplanet:8.0.0"], "meta:indexed": "2020-08-20T20:20:39.606757", "woe:alias_ITA_V": ["Stazione Tortona", "Stazione Ferroviaria di Tortona", "Stazione Ferroviaria Tortona"], "meta:updated": "2020-10-14T11:50:13.312212", "woe:hierarchy": {"continent": 24865675, "country": 23424853, "town": 0, "planet": 1, "county": 12591853, "suburb": 0, "state": 7153341, "region": 0, "localadmin": 12681393}, "woe:timezone_id": 28350914, "woe:hash": "spyr3ttnuqrz", "woe:centroid": [8.86204, 44.89957], "geom:latitude": 44.89957, "geom:longitude": 8.86204, "geom:hash": "spyr3ttnuqrz", "woe:latitude": 44.89957, "geom:centroid": [8.86204, 44.89957], "woe:longitude": 8.86204, "woe:repo": "woeplanet-poi-it", "geom:area": 0.0, "woe:scale": 19}}