{"type": "Feature", "id": 22310668, "geometry": {"type": "Point", "coordinates": [14.41976, 40.99419]}, "properties": {"woe:id": 22310668, "woe:parent_id": 711980, "woe:name": "Stazione di Cancello", "woe:placetype": 20, "woe:placetype_name": "POI", "woe:lang": "ITA", "iso:country": "IT", "meta:provider": ["geoplanet:7.3.1", "geoplanet:7.3.2", "geoplanet:7.4.0", "geoplanet:7.4.1", "geoplanet:7.5.1", "geoplanet:7.5.2", "geoplanet:7.6.0", "geoplanet:7.8.1", "geoplanet:7.9.0", "geoplanet:7.10.0", "geoplanet:8.0.0", "woeplanet:8.0.0"], "meta:indexed": "2020-08-20T20:20:39.211729", "woe:alias_ITA_V": ["Stazione Cancello Scalo", "Stazione di Cancello Scalo", "Stazione Ferroviaria di Cancello Scalo", "Stazione Ferroviaria Cancello Scalo", "Stazione Cancello", "Stazione Ferroviaria di Cancello", "Stazione Ferroviaria Cancello"], "meta:updated": "2020-10-14T11:50:14.038625", "woe:hierarchy": {"continent": 24865675, "country": 23424853, "town": 0, "planet": 1, "county": 12591875, "suburb": 0, "state": 7153333, "region": 0, "localadmin": 12676230}, "woe:timezone_id": 28350914, "woe:hash": "sr630nu0kybk", "woe:centroid": [14.41976, 40.99419], "geom:latitude": 40.99419, "geom:longitude": 14.41976, "geom:hash": "sr630nu0kybk", "woe:latitude": 40.99419, "geom:centroid": [14.41976, 40.99419], "woe:longitude": 14.41976, "woe:repo": "woeplanet-poi-it", "geom:area": 0.0, "woe:scale": 19}}