{"type": "Feature", "id": 22306088, "geometry": {"type": "Point", "coordinates": [9.12491, 39.216911]}, "properties": {"woe:id": 22306088, "woe:parent_id": 711665, "woe:name": "Stazione di Cagliari P. Za Repubblica", "woe:placetype": 20, "woe:placetype_name": "POI", "woe:lang": "ITA", "iso:country": "IT", "meta:provider": ["geoplanet:7.3.1", "geoplanet:7.3.2", "geoplanet:7.4.0", "geoplanet:7.4.1", "geoplanet:7.5.1", "geoplanet:7.5.2", "geoplanet:7.6.0", "geoplanet:7.8.1", "geoplanet:7.9.0", "geoplanet:7.10.0", "geoplanet:8.0.0", "woeplanet:8.0.0"], "meta:indexed": "2020-08-20T20:20:39.051850", "woe:alias_ITA_V": ["Stazione Ferroviaria di Cagliari", "Stazione di Cagliari", "Stazione Ferroviaria Cagliari", "Stazione Cagliari", "Stazione Cagliari P. Za Repubblica", "Stazione Ferroviaria di Cagliari P. Za Repubblica", "Stazione Ferroviaria Cagliari P. Za Repubblica"], "meta:updated": "2020-10-14T11:50:13.880924", "woe:hierarchy": {"continent": 24865675, "country": 23424853, "town": 0, "planet": 1, "county": 12591836, "suburb": 0, "state": 7153343, "region": 0, "localadmin": 20076832}, "woe:timezone_id": 28350914, "woe:hash": "snyrpehx1f44", "woe:centroid": [9.12491, 39.216911], "geom:latitude": 39.216911, "geom:longitude": 9.12491, "geom:hash": "snyrpehx1f44", "woe:latitude": 39.216911, "geom:centroid": [9.12491, 39.216911], "woe:longitude": 9.12491, "woe:repo": "woeplanet-poi-it", "geom:area": 0.0, "woe:scale": 19}}