{"type": "Feature", "id": 23145599, "properties": {"woe:id": 23145599, "woe:parent_id": 20134003, "woe:name": "Stazione di Montecalvo-Buonalbero", "woe:placetype": 20, "woe:placetype_name": "POI", "woe:lang": "ITA", "iso:country": "IT", "meta:provider": ["geoplanet:7.3.1", "geoplanet:7.3.2", "geoplanet:7.4.0", "geoplanet:7.4.1", "geoplanet:7.5.1", "geoplanet:7.5.2", "geoplanet:7.6.0", "geoplanet:7.8.1", "geoplanet:7.9.0", "geoplanet:7.10.0", "geoplanet:8.0.0", "woeplanet:8.0.0"], "meta:indexed": "2020-08-20T20:20:40.412369", "woe:alias_ITA_V": ["Stazione Montecalvo-Buonalbergo-Casalbore", "Stazione Ferroviaria di Montecalvo-Buonalbergo-Casalbore", "Stazione Ferroviaria Montecalvo-Buonalbergo-Casalbore", "Stazione di Montecalvo-Buonalbergo-Casalbore", "Stazione Montecalvo-Buonalbero", "Stazione Ferroviaria di Montecalvo-Buonalbero", "Stazione Ferroviaria Montecalvo-Buonalbero"], "meta:updated": "2020-08-22T02:30:24.893166", "woe:hierarchy": {"continent": 24865675, "country": 23424853, "town": 0, "planet": 1, "county": 12591874, "suburb": 0, "state": 7153333, "region": 0, "localadmin": 12680481}, "woe:timezone_id": 28350914, "woe:hash": "sr6dmzndudzr", "woe:centroid": [15.02744, 41.215698], "geom:latitude": 41.215698, "geom:longitude": 15.02744, "geom:hash": "sr6dmzndudzr", "woe:latitude": 41.215698, "geom:centroid": [15.02744, 41.215698], "woe:longitude": 15.02744, "woe:repo": "woeplanet-poi-it"}, "geometry": {"coordinates": [15.02744, 41.215698], "type": "Point"}}