{"type": "Feature", "id": 23158019, "properties": {"woe:id": 23158019, "woe:parent_id": 29343892, "woe:name": "Stazione di Villafranca Tirrena", "woe:placetype": 20, "woe:placetype_name": "POI", "woe:lang": "ITA", "iso:country": "IT", "meta:provider": ["geoplanet:7.3.1", "geoplanet:7.3.2", "geoplanet:7.4.0", "geoplanet:7.4.1", "geoplanet:7.5.1", "geoplanet:7.5.2", "geoplanet:7.6.0", "geoplanet:7.8.1", "geoplanet:7.9.0", "geoplanet:7.10.0", "geoplanet:8.0.0", "woeplanet:8.0.0"], "meta:indexed": "2020-08-20T20:20:40.477281", "woe:alias_ITA_V": ["Stazione Villafranca Tirrena Saponara", "Stazione Ferroviaria Villafranca Tirrena Saponara", "Stazione Ferroviaria di Villafranca Tirrena Saponara", "Stazione di Villafranca Tirrena Saponara", "Stazione Villafranca Tirrena", "Stazione Ferroviaria di Villafranca Tirrena", "Stazione Ferroviaria Villafranca Tirrena"], "meta:updated": "2020-08-22T02:30:24.925581", "woe:hierarchy": {"continent": 24865675, "country": 23424853, "town": 0, "planet": 1, "county": 12591837, "suburb": 0, "state": 7153344, "region": 0, "localadmin": 12678402}, "woe:timezone_id": 28350914, "woe:hash": "sqfcx06bpdv0", "woe:centroid": [15.42891, 38.23381], "geom:latitude": 38.23381, "geom:longitude": 15.42891, "geom:hash": "sqfcx06bpdv0", "woe:latitude": 38.23381, "geom:centroid": [15.42891, 38.23381], "woe:longitude": 15.42891, "woe:repo": "woeplanet-poi-it"}, "geometry": {"coordinates": [15.42891, 38.23381], "type": "Point"}}