{"type": "Feature", "id": 56056467, "geometry": {"type": "Point", "coordinates": [11.12584, 46.068981]}, "properties": {"woe:id": 56056467, "woe:parent_id": 725257, "woe:name": "Conservatorio F.a. Bonporti", "woe:placetype": 20, "woe:placetype_name": "POI", "woe:lang": "ITA", "iso:country": "IT", "meta:provider": ["geoplanet:7.3.1", "geoplanet:7.3.2", "geoplanet:7.4.0", "geoplanet:7.4.1", "geoplanet:7.5.1", "geoplanet:7.5.2", "geoplanet:7.6.0", "geoplanet:7.8.1", "geoplanet:7.9.0", "geoplanet:7.10.0", "geoplanet:8.0.0", "woeplanet:8.0.0"], "meta:indexed": "2020-08-20T20:20:40.656343", "meta:updated": "2020-10-14T11:50:14.257188", "woe:hierarchy": {"continent": 24865675, "country": 23424853, "town": 0, "planet": 1, "county": 12591852, "suburb": 0, "state": 7153346, "region": 0, "localadmin": 12676608}, "woe:timezone_id": 28350914, "woe:hash": "u0pyj4te6be8", "woe:centroid": [11.12584, 46.068981], "geom:latitude": 46.068981, "geom:longitude": 11.12584, "geom:hash": "u0pyj4te6be8", "woe:latitude": 46.068981, "geom:centroid": [11.12584, 46.068981], "woe:longitude": 11.12584, "woe:repo": "woeplanet-poi-it", "geom:area": 0.0, "woe:scale": 19}}