{"type": "Feature", "id": 22313497, "properties": {"woe:id": 22313497, "woe:parent_id": 20110125, "woe:name": "Stazione di Napoli Gianturco", "woe:placetype": 20, "woe:placetype_name": "POI", "woe:lang": "ITA", "iso:country": "IT", "meta:provider": ["geoplanet:7.3.1", "geoplanet:7.3.2", "geoplanet:7.4.0", "geoplanet:7.4.1", "geoplanet:7.5.1", "geoplanet:7.5.2", "geoplanet:7.6.0", "geoplanet:7.8.1", "geoplanet:7.9.0", "geoplanet:7.10.0", "geoplanet:8.0.0", "woeplanet:8.0.0"], "meta:indexed": "2020-08-20T20:20:39.301483", "woe:alias_ITA_V": ["Stazione Napoli Gianturco", "Stazione Ferroviaria di Napoli Gianturco", "Stazione Ferroviaria Napoli Gianturco"], "meta:updated": "2020-08-22T02:30:24.417001", "woe:hierarchy": {"continent": 24865675, "country": 23424853, "town": 0, "planet": 1, "county": 12591829, "suburb": 0, "state": 7153333, "region": 0, "localadmin": 20076932}, "woe:timezone_id": 28350914, "woe:hash": "sr60mjhps9v2", "woe:centroid": [14.28792, 40.853958], "geom:latitude": 40.853958, "geom:longitude": 14.28792, "geom:hash": "sr60mjhps9v2", "woe:latitude": 40.853958, "geom:centroid": [14.28792, 40.853958], "woe:longitude": 14.28792, "woe:repo": "woeplanet-poi-it"}, "geometry": {"coordinates": [14.28792, 40.853958], "type": "Point"}}