{"type": "Feature", "id": 23056887, "properties": {"woe:id": 23056887, "woe:parent_id": 20131528, "woe:name": "Museo Storico Ambientale Della Cultura Della Alpiliguri", "woe:placetype": 20, "woe:placetype_name": "POI", "woe:lang": "ITA", "iso:country": "IT", "meta:provider": ["geoplanet:7.3.1", "geoplanet:7.3.2", "geoplanet:7.4.0", "geoplanet:7.4.1", "geoplanet:7.5.1", "geoplanet:7.5.2", "geoplanet:7.6.0", "geoplanet:7.8.1", "geoplanet:7.9.0", "geoplanet:7.10.0", "geoplanet:8.0.0", "woeplanet:8.0.0"], "meta:indexed": "2020-08-20T20:20:40.104376", "meta:updated": "2020-08-22T02:30:24.750814", "woe:hierarchy": {"continent": 24865675, "country": 23424853, "town": 0, "planet": 1, "county": 12591858, "suburb": 0, "state": 7153337, "region": 0, "localadmin": 12680408}, "woe:timezone_id": 28350914, "woe:hash": "spvd9xsxvdby", "woe:centroid": [7.80671, 44.075748], "geom:latitude": 44.075748, "geom:longitude": 7.80671, "geom:hash": "spvd9xsxvdby", "woe:latitude": 44.075748, "geom:centroid": [7.80671, 44.075748], "woe:longitude": 7.80671, "woe:repo": "woeplanet-poi-it"}, "geometry": {"coordinates": [7.80671, 44.075748], "type": "Point"}}