{"type": "Feature", "id": 22307185, "properties": {"woe:id": 22307185, "woe:parent_id": 715478, "woe:name": "Stazione di Pollina", "woe:placetype": 20, "woe:placetype_name": "POI", "woe:lang": "ITA", "iso:country": "IT", "meta:provider": ["geoplanet:7.3.1", "geoplanet:7.3.2", "geoplanet:7.4.0", "geoplanet:7.4.1", "geoplanet:7.5.1", "geoplanet:7.5.2", "geoplanet:7.6.0", "geoplanet:7.8.1", "geoplanet:7.9.0", "geoplanet:7.10.0", "geoplanet:8.0.0", "woeplanet:8.0.0"], "meta:indexed": "2020-08-20T20:20:39.105429", "woe:alias_ITA_V": ["Stazione Pollina", "Stazione Ferroviaria di Pollina", "Stazione Ferroviaria Pollina"], "meta:updated": "2020-08-22T02:30:24.286773", "woe:hierarchy": {"continent": 24865675, "country": 23424853, "town": 0, "planet": 1, "county": 12591846, "suburb": 0, "state": 7153344, "region": 0, "localadmin": 12679276}, "woe:timezone_id": 28350914, "woe:hash": "sqf068gngvhr", "woe:centroid": [14.17665, 38.018002], "geom:latitude": 38.018002, "geom:longitude": 14.17665, "geom:hash": "sqf068gngvhr", "woe:latitude": 38.018002, "geom:centroid": [14.17665, 38.018002], "woe:longitude": 14.17665, "woe:repo": "woeplanet-poi-it"}, "geometry": {"coordinates": [14.17665, 38.018002], "type": "Point"}}