{"type": "Feature", "id": 22311949, "properties": {"woe:id": 22311949, "woe:parent_id": 726486, "woe:name": "Stazione di Primaticcio", "woe:placetype": 20, "woe:placetype_name": "POI", "woe:lang": "ITA", "iso:country": "IT", "meta:provider": ["geoplanet:7.3.1", "geoplanet:7.3.2", "geoplanet:7.4.0", "geoplanet:7.4.1", "geoplanet:7.5.1", "geoplanet:7.5.2", "geoplanet:7.6.0", "geoplanet:7.8.1", "geoplanet:7.9.0", "geoplanet:7.10.0", "geoplanet:8.0.0", "woeplanet:8.0.0"], "meta:indexed": "2020-08-20T20:20:39.266263", "woe:alias_ITA_V": ["Stazione Primaticcio"], "meta:updated": "2020-08-22T02:30:24.395811", "woe:hierarchy": {"continent": 24865675, "country": 23424853, "town": 0, "planet": 1, "county": 12591813, "suburb": 0, "state": 7153338, "region": 0, "localadmin": 12675801}, "woe:timezone_id": 28350914, "woe:hash": "u0n6xexudpw8", "woe:centroid": [9.12939, 45.459492], "geom:latitude": 45.459492, "geom:longitude": 9.12939, "geom:hash": "u0n6xexudpw8", "woe:latitude": 45.459492, "geom:centroid": [9.12939, 45.459492], "woe:longitude": 9.12939, "woe:repo": "woeplanet-poi-it"}, "geometry": {"coordinates": [9.12939, 45.459492], "type": "Point"}}