{"type": "Feature", "id": 22601858, "properties": {"woe:id": 22601858, "woe:parent_id": 29341798, "woe:name": "Stazione di Lentigione", "woe:placetype": 20, "woe:placetype_name": "POI", "woe:lang": "ITA", "iso:country": "IT", "meta:provider": ["geoplanet:7.3.1", "geoplanet:7.3.2", "geoplanet:7.4.0", "geoplanet:7.4.1", "geoplanet:7.5.1", "geoplanet:7.5.2", "geoplanet:7.6.0", "geoplanet:7.8.1", "geoplanet:7.9.0", "geoplanet:7.10.0", "geoplanet:8.0.0", "woeplanet:8.0.0"], "meta:indexed": "2020-08-20T20:20:39.807042", "woe:alias_ITA_V": ["Stazione Lentigione", "Stazione Ferroviaria di Lentigione", "Stazione Ferroviaria Lentigione"], "meta:updated": "2020-08-22T02:30:24.612249", "woe:hierarchy": {"continent": 24865675, "country": 23424853, "town": 0, "planet": 1, "county": 12591835, "suburb": 0, "state": 7153334, "region": 0, "localadmin": 12677096}, "woe:timezone_id": 28350914, "woe:hash": "spzrnx2ucpre", "woe:centroid": [10.48204, 44.864899], "geom:latitude": 44.864899, "geom:longitude": 10.48204, "geom:hash": "spzrnx2ucpre", "woe:latitude": 44.864899, "geom:centroid": [10.48204, 44.864899], "woe:longitude": 10.48204, "woe:repo": "woeplanet-poi-it"}, "geometry": {"coordinates": [10.48204, 44.864899], "type": "Point"}}