{"type": "Feature", "id": 22590137, "geometry": {"type": "Point", "coordinates": [10.86779, 46.29977]}, "properties": {"woe:id": 22590137, "woe:parent_id": 20124585, "woe:name": "Folgarida Ski Resort", "woe:placetype": 20, "woe:placetype_name": "POI", "woe:lang": "ENG", "iso:country": "IT", "meta:provider": ["geoplanet:7.3.1", "geoplanet:7.3.2", "geoplanet:7.4.0", "geoplanet:7.4.1", "geoplanet:7.5.1", "geoplanet:7.5.2", "geoplanet:7.6.0", "geoplanet:7.8.1", "geoplanet:7.9.0", "geoplanet:7.10.0", "geoplanet:8.0.0", "woeplanet:8.0.0"], "meta:indexed": "2020-08-20T20:20:39.745356", "meta:updated": "2020-10-14T11:50:13.358514", "woe:hierarchy": {"continent": 24865675, "country": 23424853, "town": 0, "planet": 1, "county": 12591852, "suburb": 0, "state": 7153346, "region": 0, "localadmin": 12679083}, "woe:timezone_id": 28350914, "woe:hash": "u0pxrk9etyew", "woe:centroid": [10.86779, 46.29977], "geom:latitude": 46.29977, "geom:longitude": 10.86779, "geom:hash": "u0pxrk9etyew", "woe:latitude": 46.29977, "geom:centroid": [10.86779, 46.29977], "woe:longitude": 10.86779, "woe:repo": "woeplanet-poi-it", "geom:area": 0.0, "woe:scale": 19}}