{"type": "Feature", "id": 22600038, "geometry": {"type": "Point", "coordinates": [9.35445, 44.77494]}, "properties": {"woe:id": 22600038, "woe:parent_id": 20113105, "woe:name": "Passo del P\u00e8nice", "woe:placetype": 20, "woe:placetype_name": "POI", "woe:lang": "ITA", "iso:country": "IT", "meta:provider": ["geoplanet:7.3.1", "geoplanet:7.3.2", "geoplanet:7.4.0", "geoplanet:7.4.1", "geoplanet:7.5.1", "geoplanet:7.5.2", "geoplanet:7.6.0", "geoplanet:7.8.1", "geoplanet:7.9.0", "geoplanet:7.10.0", "geoplanet:8.0.0", "woeplanet:8.0.0"], "meta:indexed": "2020-08-20T20:20:39.802035", "meta:updated": "2020-10-14T11:50:13.520816", "woe:alias_ITA_S": ["Passo del Penice"], "woe:hierarchy": {"continent": 24865675, "country": 23424853, "town": 0, "planet": 1, "county": 12591843, "suburb": 0, "state": 7153334, "region": 0, "localadmin": 12676840}, "woe:timezone_id": 28350914, "woe:hash": "spywsz58ymz2", "woe:centroid": [9.35445, 44.77494], "geom:latitude": 44.77494, "geom:longitude": 9.35445, "geom:hash": "spywsz58ymz2", "woe:latitude": 44.77494, "geom:centroid": [9.35445, 44.77494], "woe:longitude": 9.35445, "woe:repo": "woeplanet-poi-it", "geom:area": 0.0, "woe:scale": 19}}