{"type": "Feature", "id": 56056541, "geometry": {"type": "Point", "coordinates": [9.11961, 39.21344]}, "properties": {"woe:id": 56056541, "woe:parent_id": 20150226, "woe:name": "Scuola Archivistica A.p.d.", "woe:placetype": 20, "woe:placetype_name": "POI", "woe:lang": "ITA", "iso:country": "IT", "meta:provider": ["geoplanet:7.3.1", "geoplanet:7.3.2", "geoplanet:7.4.0", "geoplanet:7.4.1", "geoplanet:7.5.1", "geoplanet:7.5.2", "geoplanet:7.6.0", "geoplanet:7.8.1", "geoplanet:7.9.0", "geoplanet:7.10.0", "geoplanet:8.0.0", "woeplanet:8.0.0"], "meta:indexed": "2020-08-20T20:20:40.711213", "meta:updated": "2020-10-14T11:50:14.332423", "woe:hierarchy": {"continent": 24865675, "country": 23424853, "town": 0, "planet": 1, "county": 12591836, "suburb": 0, "state": 7153343, "region": 0, "localadmin": 20076832}, "woe:timezone_id": 28350914, "woe:hash": "snyrpd8dy741", "woe:centroid": [9.11961, 39.21344], "geom:latitude": 39.21344, "geom:longitude": 9.11961, "geom:hash": "snyrpd8dy741", "woe:latitude": 39.21344, "geom:centroid": [9.11961, 39.21344], "woe:longitude": 9.11961, "woe:repo": "woeplanet-poi-it", "geom:area": 0.0, "woe:scale": 19}}