{"type": "Feature", "id": 22593748, "geometry": {"type": "Point", "coordinates": [11.70181, 45.964729]}, "properties": {"woe:id": 22593748, "woe:parent_id": 721328, "woe:name": "Stazione di Primolano", "woe:placetype": 20, "woe:placetype_name": "POI", "woe:lang": "ITA", "iso:country": "IT", "meta:provider": ["geoplanet:7.3.1", "geoplanet:7.3.2", "geoplanet:7.4.0", "geoplanet:7.4.1", "geoplanet:7.5.1", "geoplanet:7.5.2", "geoplanet:7.6.0", "geoplanet:7.8.1", "geoplanet:7.9.0", "geoplanet:7.10.0", "geoplanet:8.0.0", "woeplanet:8.0.0"], "meta:indexed": "2020-08-20T20:20:39.757467", "woe:alias_ITA_V": ["Stazione Primolano", "Stazione Ferroviaria di Primolano", "Stazione Ferroviaria Primolano"], "meta:updated": "2020-10-14T11:50:13.425260", "woe:hierarchy": {"continent": 24865675, "country": 23424853, "town": 0, "planet": 1, "county": 12591862, "suburb": 0, "state": 7153349, "region": 0, "localadmin": 12678691}, "woe:timezone_id": 28350914, "woe:hash": "u20m6r8gzytb", "woe:centroid": [11.70181, 45.964729], "geom:latitude": 45.964729, "geom:longitude": 11.70181, "geom:hash": "u20m6r8gzytb", "woe:latitude": 45.964729, "geom:centroid": [11.70181, 45.964729], "woe:longitude": 11.70181, "woe:repo": "woeplanet-poi-it", "geom:area": 0.0, "woe:scale": 19}}