{"type": "Feature", "id": 22623089, "properties": {"woe:id": 22623089, "woe:parent_id": 720627, "woe:name": "Scuola Normale Superiore di Pisa", "woe:placetype": 20, "woe:placetype_name": "POI", "woe:lang": "ITA", "iso:country": "IT", "meta:provider": ["geoplanet:7.3.2", "geoplanet:7.4.0", "geoplanet:7.4.1", "geoplanet:7.5.1", "geoplanet:7.5.2", "geoplanet:7.6.0", "geoplanet:7.8.1", "geoplanet:7.9.0", "geoplanet:7.10.0", "geoplanet:8.0.0", "woeplanet:8.0.0"], "meta:indexed": "2020-08-20T22:04:40.727052", "woe:alias_ITA_V": ["Scuola Normale Superiore"], "meta:updated": "2020-08-22T02:30:24.651619", "woe:hierarchy": {"continent": 24865675, "country": 23424853, "town": 0, "planet": 1, "county": 12591867, "suburb": 0, "state": 7153345, "region": 0, "localadmin": 12676544}, "woe:timezone_id": 28350914, "woe:hash": "spz2swvjnhr4", "woe:centroid": [10.4002, 43.719601], "geom:latitude": 43.719601, "geom:longitude": 10.4002, "geom:hash": "spz2swvjnhr4", "woe:latitude": 43.719601, "geom:centroid": [10.4002, 43.719601], "woe:longitude": 10.4002, "woe:repo": "woeplanet-poi-it"}, "geometry": {"coordinates": [10.4002, 43.719601], "type": "Point"}}