{"type": "Feature", "id": 23067534, "geometry": {"type": "Point", "coordinates": [9.65093, 46.161659]}, "properties": {"woe:id": 23067534, "woe:parent_id": 718035, "woe:name": "Stazione di Ardenno-Masino", "woe:placetype": 20, "woe:placetype_name": "POI", "woe:lang": "ITA", "iso:country": "IT", "meta:provider": ["geoplanet:7.3.1", "geoplanet:7.3.2", "geoplanet:7.4.0", "geoplanet:7.4.1", "geoplanet:7.5.1", "geoplanet:7.5.2", "geoplanet:7.6.0", "geoplanet:7.8.1", "geoplanet:7.9.0", "geoplanet:7.10.0", "geoplanet:8.0.0", "woeplanet:8.0.0"], "meta:indexed": "2020-08-20T20:20:40.150885", "woe:alias_ITA_V": ["Stazione Ardenno Masino", "Stazione Ferroviaria Ardenno Masino", "Stazione di Ardenno Masino", "Stazione Ferroviaria di Ardenno Masino", "Stazione Ardenno-Masino", "Stazione Ferroviaria di Ardenno-Masino", "Stazione Ferroviaria Ardenno-Masino"], "meta:updated": "2020-10-14T11:50:13.191836", "woe:hierarchy": {"continent": 24865675, "country": 23424853, "town": 0, "planet": 1, "county": 12591881, "suburb": 0, "state": 7153338, "region": 0, "localadmin": 12680223}, "woe:timezone_id": 28350914, "woe:hash": "u0nyee7x4uyv", "woe:centroid": [9.65093, 46.161659], "geom:latitude": 46.161659, "geom:longitude": 9.65093, "geom:hash": "u0nyee7x4uyv", "woe:latitude": 46.161659, "geom:centroid": [9.65093, 46.161659], "woe:longitude": 9.65093, "woe:repo": "woeplanet-poi-it", "geom:area": 0.0, "woe:scale": 19}}