{"type": "Feature", "id": 22320164, "geometry": {"type": "Point", "coordinates": [10.989, 45.339001]}, "properties": {"woe:id": 22320164, "woe:parent_id": 711581, "woe:name": "Stazione di Buttapietra", "woe:placetype": 20, "woe:placetype_name": "POI", "woe:lang": "ITA", "iso:country": "IT", "meta:provider": ["geoplanet:7.3.1", "geoplanet:7.3.2", "geoplanet:7.4.0", "geoplanet:7.4.1", "geoplanet:7.5.1", "geoplanet:7.5.2", "geoplanet:7.6.0", "geoplanet:7.8.1", "geoplanet:7.9.0", "geoplanet:7.10.0", "geoplanet:8.0.0", "woeplanet:8.0.0"], "meta:indexed": "2020-08-20T20:20:39.493428", "woe:alias_ITA_V": ["Stazione Buttapietra", "Stazione Ferroviaria di Buttapietra", "Stazione Ferroviaria Buttapietra"], "meta:updated": "2020-10-14T11:50:13.793595", "woe:hierarchy": {"continent": 24865675, "country": 23424853, "town": 0, "planet": 1, "county": 12591857, "suburb": 0, "state": 7153349, "region": 0, "localadmin": 12677054}, "woe:timezone_id": 28350914, "woe:hash": "u0pcfj9yy627", "woe:centroid": [10.989, 45.339001], "geom:latitude": 45.339001, "geom:longitude": 10.989, "geom:hash": "u0pcfj9yy627", "woe:latitude": 45.339001, "geom:centroid": [10.989, 45.339001], "woe:longitude": 10.989, "woe:repo": "woeplanet-poi-it", "geom:area": 0.0, "woe:scale": 19}}