{"type": "Feature", "id": 23155532, "geometry": {"type": "Point", "coordinates": [15.64183, 38.18536]}, "properties": {"woe:id": 23155532, "woe:parent_id": 713578, "woe:name": "Stazione di Reggio di Calabria Catona", "woe:placetype": 20, "woe:placetype_name": "POI", "woe:lang": "ITA", "iso:country": "IT", "meta:provider": ["geoplanet:7.3.1", "geoplanet:7.3.2", "geoplanet:7.4.0", "geoplanet:7.4.1", "geoplanet:7.5.1", "geoplanet:7.5.2", "geoplanet:7.6.0", "geoplanet:7.8.1", "geoplanet:7.9.0", "geoplanet:7.10.0", "geoplanet:8.0.0", "woeplanet:8.0.0"], "meta:indexed": "2020-08-20T20:20:40.446501", "woe:alias_ITA_V": ["Stazione Reggio di Calabria Catona", "Stazione Ferroviaria di Reggio di Calabria Catona", "Stazione Ferroviaria Reggio di Calabria Catona"], "meta:updated": "2020-10-14T11:50:14.488563", "woe:hierarchy": {"continent": 24865675, "country": 23424853, "town": 0, "planet": 1, "county": 12591831, "suburb": 0, "state": 7153332, "region": 0, "localadmin": 12676175}, "woe:timezone_id": 28350914, "woe:hash": "sqg15zqjc51b", "woe:centroid": [15.64183, 38.18536], "geom:latitude": 38.18536, "geom:longitude": 15.64183, "geom:hash": "sqg15zqjc51b", "woe:latitude": 38.18536, "geom:centroid": [15.64183, 38.18536], "woe:longitude": 15.64183, "woe:repo": "woeplanet-poi-it", "geom:area": 0.0, "woe:scale": 19}}