{"type": "Feature", "id": 22312790, "geometry": {"type": "Point", "coordinates": [9.27282, 45.57806]}, "properties": {"woe:id": 22312790, "woe:parent_id": 719063, "woe:name": "Stazione di Monza", "woe:placetype": 20, "woe:placetype_name": "POI", "woe:lang": "ITA", "iso:country": "IT", "meta:provider": ["geoplanet:7.3.1", "geoplanet:7.3.2", "geoplanet:7.4.0", "geoplanet:7.4.1", "geoplanet:7.5.1", "geoplanet:7.5.2", "geoplanet:7.6.0", "geoplanet:7.8.1", "geoplanet:7.9.0", "geoplanet:7.10.0", "geoplanet:8.0.0", "woeplanet:8.0.0"], "meta:indexed": "2020-08-20T20:20:39.292175", "woe:alias_ITA_V": ["Stazione Monza", "Stazione Ferroviaria di Monza", "Stazione Ferroviaria Monza"], "meta:updated": "2020-10-14T11:50:14.041044", "woe:hierarchy": {"continent": 24865675, "country": 23424853, "town": 0, "planet": 1, "county": 56043515, "suburb": 0, "state": 7153338, "region": 0, "localadmin": 12680582}, "woe:timezone_id": 28350914, "woe:hash": "u0ne710r2q5w", "woe:centroid": [9.27282, 45.57806], "geom:latitude": 45.57806, "geom:longitude": 9.27282, "geom:hash": "u0ne710r2q5w", "woe:latitude": 45.57806, "geom:centroid": [9.27282, 45.57806], "woe:longitude": 9.27282, "woe:repo": "woeplanet-poi-it", "geom:area": 0.0, "woe:scale": 19}}