{"type": "Feature", "id": 22636972, "geometry": {"type": "Point", "coordinates": [12.48335, 41.900928]}, "properties": {"woe:id": 22636972, "woe:parent_id": 721943, "woe:name": "Fontana di Trevi", "woe:placetype": 20, "woe:placetype_name": "POI", "woe:lang": "ITA", "iso:country": "IT", "meta:provider": ["geoplanet:7.3.1", "geoplanet:7.3.2", "geoplanet:7.4.0", "geoplanet:7.4.1", "geoplanet:7.5.1", "geoplanet:7.5.2", "geoplanet:7.6.0", "geoplanet:7.8.1", "geoplanet:7.9.0", "geoplanet:7.10.0", "geoplanet:8.0.0", "woeplanet:8.0.0"], "meta:indexed": "2020-08-20T20:20:39.974570", "woe:alias_ENG_V": ["Trevifountain"], "woe:alias_ITA_V": ["Fontanaditrevi"], "meta:updated": "2020-10-14T11:50:13.576567", "woe:alias_ENG_P": ["Trevi Fountain"], "woe:hierarchy": {"continent": 24865675, "country": 23424853, "town": 0, "planet": 1, "county": 12591802, "suburb": 0, "state": 7153336, "region": 0, "localadmin": 12675698}, "woe:timezone_id": 28350914, "woe:hash": "sr2yk5f4e5h7", "woe:centroid": [12.48335, 41.900928], "geom:latitude": 41.900928, "geom:longitude": 12.48335, "geom:hash": "sr2yk5f4e5h7", "woe:latitude": 41.900928, "geom:centroid": [12.48335, 41.900928], "woe:longitude": 12.48335, "woe:repo": "woeplanet-poi-it", "geom:area": 0.0, "woe:scale": 19}}