{"type": "Feature", "id": 23052565, "properties": {"woe:id": 23052565, "woe:parent_id": 726326, "woe:name": "Stazione di Volpiano", "woe:placetype": 20, "woe:placetype_name": "POI", "woe:lang": "ITA", "iso:country": "IT", "meta:provider": ["geoplanet:7.3.1", "geoplanet:7.3.2", "geoplanet:7.4.0", "geoplanet:7.4.1", "geoplanet:7.5.1", "geoplanet:7.5.2", "geoplanet:7.6.0", "geoplanet:7.8.1", "geoplanet:7.9.0", "geoplanet:7.10.0", "geoplanet:8.0.0", "woeplanet:8.0.0"], "meta:indexed": "2020-08-20T20:20:40.067446", "woe:alias_ITA_V": ["Stazione Volpiano", "Stazione Ferroviaria di Volpiano", "Stazione Ferroviaria Volpiano"], "meta:updated": "2020-08-22T02:30:24.734044", "woe:hierarchy": {"continent": 24865675, "country": 23424853, "town": 0, "planet": 1, "county": 12591807, "suburb": 0, "state": 7153341, "region": 0, "localadmin": 12681578}, "woe:timezone_id": 28350914, "woe:hash": "u0j91h99fc92", "woe:centroid": [7.7805, 45.200809], "geom:latitude": 45.200809, "geom:longitude": 7.7805, "geom:hash": "u0j91h99fc92", "woe:latitude": 45.200809, "geom:centroid": [7.7805, 45.200809], "woe:longitude": 7.7805, "woe:repo": "woeplanet-poi-it"}, "geometry": {"coordinates": [7.7805, 45.200809], "type": "Point"}}