{"type": "Feature", "id": 22596136, "properties": {"woe:id": 22596136, "woe:parent_id": 715201, "woe:name": "Stazione di Este", "woe:placetype": 20, "woe:placetype_name": "POI", "woe:lang": "ITA", "iso:country": "IT", "meta:provider": ["geoplanet:7.3.1", "geoplanet:7.3.2", "geoplanet:7.4.0", "geoplanet:7.4.1", "geoplanet:7.5.1", "geoplanet:7.5.2", "geoplanet:7.6.0", "geoplanet:7.8.1", "geoplanet:7.9.0", "geoplanet:7.10.0", "geoplanet:8.0.0", "woeplanet:8.0.0"], "meta:indexed": "2020-08-20T20:20:39.786273", "woe:alias_ITA_V": ["Stazione Este", "Stazione Ferroviaria di Este", "Stazione Ferroviaria Este"], "meta:updated": "2020-08-22T02:30:24.604354", "woe:hierarchy": {"continent": 24865675, "country": 23424853, "town": 0, "planet": 1, "county": 12591804, "suburb": 0, "state": 7153349, "region": 0, "localadmin": 12679164}, "woe:timezone_id": 28350914, "woe:hash": "u20332m09f7p", "woe:centroid": [11.66344, 45.221199], "geom:latitude": 45.221199, "geom:longitude": 11.66344, "geom:hash": "u20332m09f7p", "woe:latitude": 45.221199, "geom:centroid": [11.66344, 45.221199], "woe:longitude": 11.66344, "woe:repo": "woeplanet-poi-it"}, "geometry": {"coordinates": [11.66344, 45.221199], "type": "Point"}}