{"type": "Feature", "id": 22322531, "geometry": {"type": "Point", "coordinates": [11.89142, 45.45343]}, "properties": {"woe:id": 22322531, "woe:parent_id": 725952, "woe:name": "Stazione di Vigodarzere", "woe:placetype": 20, "woe:placetype_name": "POI", "woe:lang": "ITA", "iso:country": "IT", "meta:provider": ["geoplanet:7.3.1", "geoplanet:7.3.2", "geoplanet:7.4.0", "geoplanet:7.4.1", "geoplanet:7.5.1", "geoplanet:7.5.2", "geoplanet:7.6.0", "geoplanet:7.8.1", "geoplanet:7.9.0", "geoplanet:7.10.0", "geoplanet:8.0.0", "woeplanet:8.0.0"], "meta:indexed": "2020-08-20T20:20:39.552153", "woe:alias_ITA_V": ["Stazione Vigodarzere", "Stazione Ferroviaria di Vigodarzere", "Stazione Ferroviaria Vigodarzere"], "meta:updated": "2020-10-14T11:50:13.749444", "woe:hierarchy": {"continent": 24865675, "country": 23424853, "town": 0, "planet": 1, "county": 12591804, "suburb": 0, "state": 7153349, "region": 0, "localadmin": 12682427}, "woe:timezone_id": 28350914, "woe:hash": "u206wde16jmr", "woe:centroid": [11.89142, 45.45343], "geom:latitude": 45.45343, "geom:longitude": 11.89142, "geom:hash": "u206wde16jmr", "woe:latitude": 45.45343, "geom:centroid": [11.89142, 45.45343], "woe:longitude": 11.89142, "woe:repo": "woeplanet-poi-it", "geom:area": 0.0, "woe:scale": 19}}