{"type": "Feature", "id": 22304002, "geometry": {"type": "Point", "coordinates": [13.09423, 42.397499]}, "properties": {"woe:id": 22304002, "woe:parent_id": 721824, "woe:name": "Stazione di Rocca di Fondi", "woe:placetype": 20, "woe:placetype_name": "POI", "woe:lang": "ITA", "iso:country": "IT", "meta:provider": ["geoplanet:7.3.1", "geoplanet:7.3.2", "geoplanet:7.4.0", "geoplanet:7.4.1", "geoplanet:7.5.1", "geoplanet:7.5.2", "geoplanet:7.6.0", "geoplanet:7.8.1", "geoplanet:7.9.0", "geoplanet:7.10.0", "geoplanet:8.0.0", "woeplanet:8.0.0"], "meta:indexed": "2020-08-20T20:20:39.004228", "woe:alias_ITA_V": ["Stazione Rocca di Fondi", "Stazione Ferroviaria di Rocca di Fondi", "Stazione Ferroviaria Rocca di Fondi"], "meta:updated": "2020-10-14T11:50:13.971334", "woe:hierarchy": {"continent": 24865675, "country": 23424853, "town": 0, "planet": 1, "county": 12591828, "suburb": 0, "state": 7153336, "region": 0, "localadmin": 12676129}, "woe:timezone_id": 28350914, "woe:hash": "sr931ynzmdts", "woe:centroid": [13.09423, 42.397499], "geom:latitude": 42.397499, "geom:longitude": 13.09423, "geom:hash": "sr931ynzmdts", "woe:latitude": 42.397499, "geom:centroid": [13.09423, 42.397499], "woe:longitude": 13.09423, "woe:repo": "woeplanet-poi-it", "geom:area": 0.0, "woe:scale": 19}}