{"type": "Feature", "id": 22308433, "geometry": {"type": "Point", "coordinates": [13.39669, 43.630459]}, "properties": {"woe:id": 22308433, "woe:parent_id": 715264, "woe:name": "Stazione di Falconara", "woe:placetype": 20, "woe:placetype_name": "POI", "woe:lang": "ITA", "iso:country": "IT", "meta:provider": ["geoplanet:7.3.1", "geoplanet:7.3.2", "geoplanet:7.4.0", "geoplanet:7.4.1", "geoplanet:7.5.1", "geoplanet:7.5.2", "geoplanet:7.6.0", "geoplanet:7.8.1", "geoplanet:7.9.0", "geoplanet:7.10.0", "geoplanet:8.0.0", "woeplanet:8.0.0"], "meta:indexed": "2020-08-20T20:20:39.147768", "woe:alias_ITA_V": ["Stazione di Falconara Marittima", "Stazione Ferroviaria di Falconara Marittima", "Stazione Ferroviaria Falconara Marittima", "Stazione Falconara Marittima", "Stazione Falconara", "Stazione Ferroviaria di Falconara", "Stazione Ferroviaria Falconara"], "meta:updated": "2020-10-14T11:50:13.989823", "woe:hierarchy": {"continent": 24865675, "country": 23424853, "town": 0, "planet": 1, "county": 12591847, "suburb": 0, "state": 7153339, "region": 0, "localadmin": 12678039}, "woe:timezone_id": 28350914, "woe:hash": "src80yejve01", "woe:centroid": [13.39669, 43.630459], "geom:latitude": 43.630459, "geom:longitude": 13.39669, "geom:hash": "src80yejve01", "woe:latitude": 43.630459, "geom:centroid": [13.39669, 43.630459], "woe:longitude": 13.39669, "woe:repo": "woeplanet-poi-it", "geom:area": 0.0, "woe:scale": 19}}