{"type": "Feature", "id": 23158014, "properties": {"woe:id": 23158014, "woe:parent_id": 723647, "woe:name": "Stazione di Santa Teresa di Riva", "woe:placetype": 20, "woe:placetype_name": "POI", "woe:lang": "ITA", "iso:country": "IT", "meta:provider": ["geoplanet:7.3.1", "geoplanet:7.3.2", "geoplanet:7.4.0", "geoplanet:7.4.1", "geoplanet:7.5.1", "geoplanet:7.5.2", "geoplanet:7.6.0", "geoplanet:7.8.1", "geoplanet:7.9.0", "geoplanet:7.10.0", "geoplanet:8.0.0", "woeplanet:8.0.0"], "meta:indexed": "2020-08-20T20:20:40.476502", "woe:alias_ITA_V": ["Stazione Santa Teresa di Riva", "Stazione Ferroviaria di Santa Teresa di Riva", "Stazione Ferroviaria Santa Teresa di Riva"], "meta:updated": "2020-08-22T02:30:24.925262", "woe:hierarchy": {"continent": 24865675, "country": 23424853, "town": 0, "planet": 1, "county": 12591837, "suburb": 0, "state": 7153344, "region": 0, "localadmin": 12679435}, "woe:timezone_id": 28350914, "woe:hash": "sqdzvevcrt7x", "woe:centroid": [15.36711, 37.945648], "geom:latitude": 37.945648, "geom:longitude": 15.36711, "geom:hash": "sqdzvevcrt7x", "woe:latitude": 37.945648, "geom:centroid": [15.36711, 37.945648], "woe:longitude": 15.36711, "woe:repo": "woeplanet-poi-it"}, "geometry": {"coordinates": [15.36711, 37.945648], "type": "Point"}}