{"type": "Feature", "id": 22593842, "geometry": {"type": "Point", "coordinates": [11.47674, 45.69997]}, "properties": {"woe:id": 22593842, "woe:parent_id": 724885, "woe:name": "Stazione di Thiene", "woe:placetype": 20, "woe:placetype_name": "POI", "woe:lang": "ITA", "iso:country": "IT", "meta:provider": ["geoplanet:7.3.1", "geoplanet:7.3.2", "geoplanet:7.4.0", "geoplanet:7.4.1", "geoplanet:7.5.1", "geoplanet:7.5.2", "geoplanet:7.6.0", "geoplanet:7.8.1", "geoplanet:7.9.0", "geoplanet:7.10.0", "geoplanet:8.0.0", "woeplanet:8.0.0"], "meta:indexed": "2020-08-20T20:20:39.769829", "woe:alias_ITA_V": ["Stazione Thiene", "Stazione Ferroviaria di Thiene", "Stazione Ferroviaria Thiene"], "meta:updated": "2020-10-14T11:50:13.327784", "woe:hierarchy": {"continent": 24865675, "country": 23424853, "town": 0, "planet": 1, "county": 12591862, "suburb": 0, "state": 7153349, "region": 0, "localadmin": 12678472}, "woe:timezone_id": 28350914, "woe:hash": "u205vpmje7ve", "woe:centroid": [11.47674, 45.69997], "geom:latitude": 45.69997, "geom:longitude": 11.47674, "geom:hash": "u205vpmje7ve", "woe:latitude": 45.69997, "geom:centroid": [11.47674, 45.69997], "woe:longitude": 11.47674, "woe:repo": "woeplanet-poi-it", "geom:area": 0.0, "woe:scale": 19}}