{"type": "Feature", "id": 23121788, "geometry": {"type": "Point", "coordinates": [11.25783, 43.770538]}, "properties": {"woe:id": 23121788, "woe:parent_id": 715496, "woe:name": "Museo Nazionale del Bargello", "woe:placetype": 20, "woe:placetype_name": "POI", "woe:lang": "ITA", "iso:country": "IT", "meta:provider": ["geoplanet:7.3.1", "geoplanet:7.3.2", "geoplanet:7.4.0", "geoplanet:7.4.1", "geoplanet:7.5.1", "geoplanet:7.5.2", "geoplanet:7.6.0", "geoplanet:7.8.1", "geoplanet:7.9.0", "geoplanet:7.10.0", "geoplanet:8.0.0", "woeplanet:8.0.0"], "meta:indexed": "2020-08-20T20:20:40.306149", "meta:updated": "2020-10-14T11:50:14.437314", "woe:hierarchy": {"continent": 24865675, "country": 23424853, "town": 0, "planet": 1, "county": 12591818, "suburb": 0, "state": 7153345, "region": 0, "localadmin": 12676187}, "woe:timezone_id": 28350914, "woe:hash": "srb100jty7wm", "woe:centroid": [11.25783, 43.770538], "geom:latitude": 43.770538, "geom:longitude": 11.25783, "geom:hash": "srb100jty7wm", "woe:latitude": 43.770538, "geom:centroid": [11.25783, 43.770538], "woe:longitude": 11.25783, "woe:repo": "woeplanet-poi-it", "geom:area": 0.0, "woe:scale": 19}}