{"type": "Feature", "id": 22322119, "geometry": {"type": "Point", "coordinates": [7.66404, 43.778568]}, "properties": {"woe:id": 22322119, "woe:parent_id": 711134, "woe:name": "Stazione di Bordighera", "woe:placetype": 20, "woe:placetype_name": "POI", "woe:lang": "ITA", "iso:country": "IT", "meta:provider": ["geoplanet:7.3.1", "geoplanet:7.3.2", "geoplanet:7.4.0", "geoplanet:7.4.1", "geoplanet:7.5.1", "geoplanet:7.5.2", "geoplanet:7.6.0", "geoplanet:7.8.1", "geoplanet:7.9.0", "geoplanet:7.10.0", "geoplanet:8.0.0", "woeplanet:8.0.0"], "meta:indexed": "2020-08-20T20:20:39.535755", "woe:alias_ITA_V": ["Stazione Bordighera", "Stazione Ferroviaria di Bordighera", "Stazione Ferroviaria Bordighera"], "meta:updated": "2020-10-14T11:50:13.889665", "woe:hierarchy": {"continent": 24865675, "country": 23424853, "town": 0, "planet": 1, "county": 12591858, "suburb": 0, "state": 7153337, "region": 0, "localadmin": 12676904}, "woe:timezone_id": 28350914, "woe:hash": "spv3n3su9hd6", "woe:centroid": [7.66404, 43.778568], "geom:latitude": 43.778568, "geom:longitude": 7.66404, "geom:hash": "spv3n3su9hd6", "woe:latitude": 43.778568, "geom:centroid": [7.66404, 43.778568], "woe:longitude": 7.66404, "woe:repo": "woeplanet-poi-it", "geom:area": 0.0, "woe:scale": 19}}