{"type": "Feature", "id": 22608240, "properties": {"woe:id": 22608240, "woe:parent_id": 721535, "woe:name": "Mausoleo di Teodorico", "woe:placetype": 20, "woe:placetype_name": "POI", "woe:lang": "ITA", "iso:country": "IT", "meta:provider": ["geoplanet:7.3.1", "geoplanet:7.3.2", "geoplanet:7.4.0", "geoplanet:7.4.1", "geoplanet:7.5.1", "geoplanet:7.5.2", "geoplanet:7.6.0", "geoplanet:7.8.1", "geoplanet:7.9.0", "geoplanet:7.10.0", "geoplanet:8.0.0", "woeplanet:8.0.0"], "meta:indexed": "2020-08-20T20:20:39.838802", "meta:updated": "2020-08-22T02:30:24.627361", "woe:hierarchy": {"continent": 24865675, "country": 23424853, "town": 0, "planet": 1, "county": 12591886, "suburb": 0, "state": 7153334, "region": 0, "localadmin": 12676061}, "woe:timezone_id": 28350914, "woe:hash": "srbstz4me7pt", "woe:centroid": [12.20905, 44.424179], "geom:latitude": 44.424179, "geom:longitude": 12.20905, "geom:hash": "srbstz4me7pt", "woe:latitude": 44.424179, "geom:centroid": [12.20905, 44.424179], "woe:longitude": 12.20905, "woe:repo": "woeplanet-poi-it"}, "geometry": {"coordinates": [12.20905, 44.424179], "type": "Point"}}