{"type": "Feature", "id": 23144091, "properties": {"woe:id": 23144091, "woe:parent_id": 29340017, "woe:name": "Stazione di Circumvesuviana di Moregine", "woe:placetype": 20, "woe:placetype_name": "POI", "woe:lang": "ITA", "iso:country": "IT", "meta:provider": ["geoplanet:7.3.1", "geoplanet:7.3.2", "geoplanet:7.4.0", "geoplanet:7.4.1", "geoplanet:7.5.1", "geoplanet:7.5.2", "geoplanet:7.6.0", "geoplanet:7.8.1", "geoplanet:7.9.0", "geoplanet:7.10.0", "geoplanet:8.0.0", "woeplanet:8.0.0"], "meta:indexed": "2020-08-20T20:20:40.400157", "woe:alias_ITA_V": ["Stazione Circumvesuviana di Moregine", "Stazione Ferroviaria di Circumvesuviana di Moregine", "Stazione Ferroviaria Circumvesuviana di Moregine"], "meta:updated": "2020-08-22T02:30:24.887702", "woe:hierarchy": {"continent": 24865675, "country": 23424853, "town": 0, "planet": 1, "county": 12591829, "suburb": 0, "state": 7153333, "region": 0, "localadmin": 12681198}, "woe:timezone_id": 28350914, "woe:hash": "sr4rc85tz393", "woe:centroid": [14.4851, 40.7383], "geom:latitude": 40.7383, "geom:longitude": 14.4851, "geom:hash": "sr4rc85tz393", "woe:latitude": 40.7383, "geom:centroid": [14.4851, 40.7383], "woe:longitude": 14.4851, "woe:repo": "woeplanet-poi-it"}, "geometry": {"coordinates": [14.4851, 40.7383], "type": "Point"}}