{"type": "Feature", "id": 22554915, "geometry": {"type": "Point", "coordinates": [8.03819, 43.893219]}, "properties": {"woe:id": 22554915, "woe:parent_id": 716647, "woe:name": "Museo Dell'olivo", "woe:placetype": 20, "woe:placetype_name": "POI", "woe:lang": "ITA", "iso:country": "IT", "meta:provider": ["geoplanet:7.3.1", "geoplanet:7.3.2", "geoplanet:7.4.0", "geoplanet:7.4.1", "geoplanet:7.5.1", "geoplanet:7.5.2", "geoplanet:7.6.0", "geoplanet:7.8.1", "geoplanet:7.9.0", "geoplanet:7.10.0", "geoplanet:8.0.0", "woeplanet:8.0.0"], "meta:indexed": "2020-08-20T20:20:39.607615", "meta:updated": "2020-10-14T11:50:13.231822", "woe:hierarchy": {"continent": 24865675, "country": 23424853, "town": 0, "planet": 1, "county": 12591858, "suburb": 0, "state": 7153337, "region": 0, "localadmin": 12676279}, "woe:timezone_id": 28350914, "woe:hash": "spv9wyt0x3hf", "woe:centroid": [8.03819, 43.893219], "geom:latitude": 43.893219, "geom:longitude": 8.03819, "geom:hash": "spv9wyt0x3hf", "woe:latitude": 43.893219, "geom:centroid": [8.03819, 43.893219], "woe:longitude": 8.03819, "woe:repo": "woeplanet-poi-it", "geom:area": 0.0, "woe:scale": 19}}