{"type": "Feature", "id": 22322516, "geometry": {"type": "Point", "coordinates": [11.71495, 45.62178]}, "properties": {"woe:id": 22322516, "woe:parent_id": 719668, "woe:name": "Stazione di Carmignano di Brenta", "woe:placetype": 20, "woe:placetype_name": "POI", "woe:lang": "ITA", "iso:country": "IT", "meta:provider": ["geoplanet:7.3.1", "geoplanet:7.3.2", "geoplanet:7.4.0", "geoplanet:7.4.1", "geoplanet:7.5.1", "geoplanet:7.5.2", "geoplanet:7.6.0", "geoplanet:7.8.1", "geoplanet:7.9.0", "geoplanet:7.10.0", "geoplanet:8.0.0", "woeplanet:8.0.0"], "meta:indexed": "2020-08-20T20:20:39.547944", "woe:alias_ITA_V": ["Stazione Carmignano di Brenta", "Stazione Ferroviaria di Carmignano di Brenta", "Stazione Ferroviaria Carmignano di Brenta"], "meta:updated": "2020-10-14T11:50:13.755494", "woe:hierarchy": {"continent": 24865675, "country": 23424853, "town": 0, "planet": 1, "county": 12591804, "suburb": 0, "state": 7153349, "region": 0, "localadmin": 12677706}, "woe:timezone_id": 28350914, "woe:hash": "u207d94w4h5y", "woe:centroid": [11.71495, 45.62178], "geom:latitude": 45.62178, "geom:longitude": 11.71495, "geom:hash": "u207d94w4h5y", "woe:latitude": 45.62178, "geom:centroid": [11.71495, 45.62178], "woe:longitude": 11.71495, "woe:repo": "woeplanet-poi-it", "geom:area": 0.0, "woe:scale": 19}}