{"type": "Feature", "id": 22322587, "properties": {"woe:id": 22322587, "woe:parent_id": 726105, "woe:name": "Stazione di Villafranca di Verona", "woe:placetype": 20, "woe:placetype_name": "POI", "woe:lang": "ITA", "iso:country": "IT", "meta:provider": ["geoplanet:7.3.1", "geoplanet:7.3.2", "geoplanet:7.4.0", "geoplanet:7.4.1", "geoplanet:7.5.1", "geoplanet:7.5.2", "geoplanet:7.6.0", "geoplanet:7.8.1", "geoplanet:7.9.0", "geoplanet:7.10.0", "geoplanet:8.0.0", "woeplanet:8.0.0"], "meta:indexed": "2020-08-20T20:20:39.556162", "woe:alias_ITA_V": ["Stazione Villafranca di Verona", "Stazione Ferroviaria di Villafranca di Verona", "Stazione Ferroviaria Villafranca di Verona"], "meta:updated": "2020-08-22T02:30:24.516247", "woe:hierarchy": {"continent": 24865675, "country": 23424853, "town": 0, "planet": 1, "county": 12591857, "suburb": 0, "state": 7153349, "region": 0, "localadmin": 12676381}, "woe:timezone_id": 28350914, "woe:hash": "u0p9yzey8g1x", "woe:centroid": [10.84869, 45.349949], "geom:latitude": 45.349949, "geom:longitude": 10.84869, "geom:hash": "u0p9yzey8g1x", "woe:latitude": 45.349949, "geom:centroid": [10.84869, 45.349949], "woe:longitude": 10.84869, "woe:repo": "woeplanet-poi-it"}, "geometry": {"coordinates": [10.84869, 45.349949], "type": "Point"}}