{"type": "Feature", "id": 56056380, "geometry": {"type": "Point", "coordinates": [9.33612, 45.572681]}, "properties": {"woe:id": 56056380, "woe:parent_id": 709856, "woe:name": "Winkler", "woe:placetype": 20, "woe:placetype_name": "POI", "woe:lang": "ITA", "iso:country": "IT", "meta:provider": ["geoplanet:7.3.1", "geoplanet:7.3.2", "geoplanet:7.4.0", "geoplanet:7.4.1", "geoplanet:7.5.1", "geoplanet:7.5.2", "geoplanet:7.6.0", "geoplanet:7.8.1", "geoplanet:7.9.0", "geoplanet:7.10.0", "geoplanet:8.0.0", "woeplanet:8.0.0"], "meta:indexed": "2020-08-20T20:20:40.591198", "meta:updated": "2020-10-14T11:50:14.307474", "woe:hierarchy": {"continent": 24865675, "country": 23424853, "town": 0, "planet": 1, "county": 56043515, "suburb": 0, "state": 7153338, "region": 0, "localadmin": 12675833}, "woe:timezone_id": 28350914, "woe:hash": "u0nek2q2577x", "woe:centroid": [9.33612, 45.572681], "geom:latitude": 45.572681, "geom:longitude": 9.33612, "geom:hash": "u0nek2q2577x", "woe:latitude": 45.572681, "geom:centroid": [9.33612, 45.572681], "woe:longitude": 9.33612, "woe:repo": "woeplanet-poi-it", "geom:area": 0.0, "woe:scale": 19}}