{"type": "Feature", "id": 23129175, "properties": {"woe:id": 23129175, "woe:parent_id": 29339776, "woe:name": "Stazione di Scanzano Belfiore", "woe:placetype": 20, "woe:placetype_name": "POI", "woe:lang": "ITA", "iso:country": "IT", "meta:provider": ["geoplanet:7.3.1", "geoplanet:7.3.2", "geoplanet:7.4.0", "geoplanet:7.4.1", "geoplanet:7.5.1", "geoplanet:7.5.2", "geoplanet:7.6.0", "geoplanet:7.8.1", "geoplanet:7.9.0", "geoplanet:7.10.0", "geoplanet:8.0.0", "woeplanet:8.0.0"], "meta:indexed": "2020-08-20T20:20:40.329751", "woe:alias_ITA_V": ["Stazione di Scanzano", "Stazione Ferroviaria Scanzano", "Stazione Scanzano", "Stazione Ferroviaria di Scanzano", "Stazione Scanzano Belfiore", "Stazione Ferroviaria di Scanzano Belfiore", "Stazione Ferroviaria Scanzano Belfiore"], "meta:updated": "2020-08-22T02:30:24.855404", "woe:hierarchy": {"continent": 24865675, "country": 23424853, "town": 0, "planet": 1, "county": 12591817, "suburb": 0, "state": 7153347, "region": 0, "localadmin": 12676104}, "woe:timezone_id": 28350914, "woe:hash": "sr9h9bgp44pq", "woe:centroid": [12.73737, 42.983849], "geom:latitude": 42.983849, "geom:longitude": 12.73737, "geom:hash": "sr9h9bgp44pq", "woe:latitude": 42.983849, "geom:centroid": [12.73737, 42.983849], "woe:longitude": 12.73737, "woe:repo": "woeplanet-poi-it"}, "geometry": {"coordinates": [12.73737, 42.983849], "type": "Point"}}