{"type": "Feature", "id": 22542912, "properties": {"woe:id": 22542912, "woe:parent_id": 716739, "woe:name": "Torre di Santo Stefano", "woe:placetype": 20, "woe:placetype_name": "POI", "woe:lang": "ITA", "iso:country": "IT", "meta:provider": ["geoplanet:7.3.1", "geoplanet:7.3.2", "geoplanet:7.4.0", "geoplanet:7.4.1", "geoplanet:7.5.1", "geoplanet:7.5.2", "geoplanet:7.6.0", "geoplanet:7.8.1", "geoplanet:7.9.0", "geoplanet:7.10.0", "geoplanet:8.0.0", "woeplanet:8.0.0"], "meta:indexed": "2020-08-20T20:20:39.565868", "meta:updated": "2020-08-22T02:30:24.520469", "woe:hierarchy": {"continent": 24865675, "country": 23424853, "town": 0, "planet": 1, "county": 12591807, "suburb": 0, "state": 7153341, "region": 0, "localadmin": 12679248}, "woe:timezone_id": 28350914, "woe:hash": "u0jdekdp5jj9", "woe:centroid": [7.88008, 45.465401], "geom:latitude": 45.465401, "geom:longitude": 7.88008, "geom:hash": "u0jdekdp5jj9", "woe:latitude": 45.465401, "geom:centroid": [7.88008, 45.465401], "woe:longitude": 7.88008, "woe:repo": "woeplanet-poi-it"}, "geometry": {"coordinates": [7.88008, 45.465401], "type": "Point"}}