{"type": "Feature", "id": 22548509, "geometry": {"type": "Point", "coordinates": [7.68954, 45.069481]}, "properties": {"woe:id": 22548509, "woe:parent_id": 725003, "woe:name": "Universit\u00e0 degli Studi di Torino", "woe:placetype": 20, "woe:placetype_name": "POI", "woe:lang": "ITA", "iso:country": "IT", "meta:provider": ["geoplanet:7.3.1", "geoplanet:7.3.2", "geoplanet:7.4.0", "geoplanet:7.4.1", "geoplanet:7.5.1", "geoplanet:7.5.2", "geoplanet:7.6.0", "geoplanet:7.8.1", "geoplanet:7.9.0", "geoplanet:7.10.0", "geoplanet:8.0.0", "woeplanet:8.0.0"], "meta:indexed": "2020-08-20T20:20:39.594980", "woe:alias_ITA_V": ["Universita Degli Studi", "Universit\u00e0 Degli Studi"], "meta:updated": "2020-10-14T11:50:13.237764", "woe:alias_ITA_S": ["Universita degli Studi di Torino"], "woe:hierarchy": {"continent": 24865675, "country": 23424853, "town": 0, "planet": 1, "county": 12591807, "suburb": 0, "state": 7153341, "region": 0, "localadmin": 12675704}, "woe:timezone_id": 28350914, "woe:hash": "u0j2quxkg20w", "woe:centroid": [7.68954, 45.069481], "geom:latitude": 45.069481, "geom:longitude": 7.68954, "geom:hash": "u0j2quxkg20w", "woe:latitude": 45.069481, "geom:centroid": [7.68954, 45.069481], "woe:longitude": 7.68954, "woe:repo": "woeplanet-poi-it", "geom:area": 0.0, "woe:scale": 19}}