{"type": "Feature", "id": 22310499, "geometry": {"type": "Point", "coordinates": [10.33583, 43.554241]}, "properties": {"woe:id": 22310499, "woe:parent_id": 29336703, "woe:name": "Stazione di Livorno Centrale", "woe:placetype": 20, "woe:placetype_name": "POI", "woe:lang": "ITA", "iso:country": "IT", "meta:provider": ["geoplanet:7.3.1", "geoplanet:7.3.2", "geoplanet:7.4.0", "geoplanet:7.4.1", "geoplanet:7.5.1", "geoplanet:7.5.2", "geoplanet:7.6.0", "geoplanet:7.8.1", "geoplanet:7.9.0", "geoplanet:7.10.0", "geoplanet:8.0.0", "woeplanet:8.0.0"], "meta:indexed": "2020-08-20T20:20:39.205733", "woe:alias_ITA_V": ["Stazione Livorno Centrale", "Stazione Ferroviaria di Livorno Centrale", "Stazione Ferroviaria Livorno Centrale"], "meta:updated": "2020-10-14T11:50:13.897799", "woe:hierarchy": {"continent": 24865675, "country": 23424853, "town": 0, "planet": 1, "county": 12591891, "suburb": 0, "state": 7153345, "region": 0, "localadmin": 12676124}, "woe:timezone_id": 28350914, "woe:hash": "spxrg0y3f6cr", "woe:centroid": [10.33583, 43.554241], "geom:latitude": 43.554241, "geom:longitude": 10.33583, "geom:hash": "spxrg0y3f6cr", "woe:latitude": 43.554241, "geom:centroid": [10.33583, 43.554241], "woe:longitude": 10.33583, "woe:repo": "woeplanet-poi-it", "geom:area": 0.0, "woe:scale": 19}}