{"type": "Feature", "id": 22585500, "geometry": {"type": "Point", "coordinates": [10.78575, 45.147831]}, "properties": {"woe:id": 22585500, "woe:parent_id": 717803, "woe:name": "Palazzo Te", "woe:placetype": 20, "woe:placetype_name": "POI", "woe:lang": "ITA", "iso:country": "IT", "meta:provider": ["geoplanet:7.3.1", "geoplanet:7.3.2", "geoplanet:7.4.0", "geoplanet:7.4.1", "geoplanet:7.5.1", "geoplanet:7.5.2", "geoplanet:7.6.0", "geoplanet:7.8.1", "geoplanet:7.9.0", "geoplanet:7.10.0", "geoplanet:8.0.0", "woeplanet:8.0.0"], "meta:indexed": "2020-08-20T20:20:39.729946", "meta:updated": "2020-10-14T11:50:13.385020", "woe:hierarchy": {"continent": 24865675, "country": 23424853, "town": 0, "planet": 1, "county": 12591844, "suburb": 0, "state": 7153338, "region": 0, "localadmin": 12680140}, "woe:timezone_id": 28350914, "woe:hash": "u0p8v6vvnjwn", "woe:centroid": [10.78575, 45.147831], "geom:latitude": 45.147831, "geom:longitude": 10.78575, "geom:hash": "u0p8v6vvnjwn", "woe:latitude": 45.147831, "geom:centroid": [10.78575, 45.147831], "woe:longitude": 10.78575, "woe:repo": "woeplanet-poi-it", "geom:area": 0.0, "woe:scale": 19}}