{"type": "Feature", "id": 22313094, "properties": {"woe:id": 22313094, "woe:parent_id": 713139, "woe:name": "Stazione di Casoria Afragola", "woe:placetype": 20, "woe:placetype_name": "POI", "woe:lang": "ITA", "iso:country": "IT", "meta:provider": ["geoplanet:7.3.1", "geoplanet:7.3.2", "geoplanet:7.4.0", "geoplanet:7.4.1", "geoplanet:7.5.1", "geoplanet:7.5.2", "geoplanet:7.6.0", "geoplanet:7.8.1", "geoplanet:7.9.0", "geoplanet:7.10.0", "geoplanet:8.0.0", "woeplanet:8.0.0"], "meta:indexed": "2020-08-20T20:20:39.296653", "woe:alias_ITA_V": ["Stazione di Casoria-Afragola", "Stazione Ferroviaria di Casoria-Afragola", "Stazione Ferroviaria Casoria-Afragola", "Stazione Casoria-Afragola", "Stazione Casoria Afragola", "Stazione Ferroviaria di Casoria Afragola", "Stazione Ferroviaria Casoria Afragola"], "meta:updated": "2020-08-22T02:30:24.414577", "woe:hierarchy": {"continent": 24865675, "country": 23424853, "town": 0, "planet": 1, "county": 12591829, "suburb": 0, "state": 7153333, "region": 0, "localadmin": 12678130}, "woe:timezone_id": 28350914, "woe:hash": "sr60tqgzpc7r", "woe:centroid": [14.2987, 40.907429], "geom:latitude": 40.907429, "geom:longitude": 14.2987, "geom:hash": "sr60tqgzpc7r", "woe:latitude": 40.907429, "geom:centroid": [14.2987, 40.907429], "woe:longitude": 14.2987, "woe:repo": "woeplanet-poi-it"}, "geometry": {"coordinates": [14.2987, 40.907429], "type": "Point"}}