{"type": "Feature", "id": 22320293, "geometry": {"type": "Point", "coordinates": [9.30108, 45.07922]}, "properties": {"woe:id": 22320293, "woe:parent_id": 724576, "woe:name": "Stazione di Stradella", "woe:placetype": 20, "woe:placetype_name": "POI", "woe:lang": "ITA", "iso:country": "IT", "meta:provider": ["geoplanet:7.3.1", "geoplanet:7.3.2", "geoplanet:7.4.0", "geoplanet:7.4.1", "geoplanet:7.5.1", "geoplanet:7.5.2", "geoplanet:7.6.0", "geoplanet:7.8.1", "geoplanet:7.9.0", "geoplanet:7.10.0", "geoplanet:8.0.0", "woeplanet:8.0.0"], "meta:indexed": "2020-08-20T20:20:39.503270", "woe:alias_ITA_V": ["Stazione Stradella", "Stazione Ferroviaria di Stradella", "Stazione Ferroviaria Stradella"], "meta:updated": "2020-10-14T11:50:13.834971", "woe:hierarchy": {"continent": 24865675, "country": 23424853, "town": 0, "planet": 1, "county": 12591878, "suburb": 0, "state": 7153338, "region": 0, "localadmin": 12682101}, "woe:timezone_id": 28350914, "woe:hash": "u0n87wkv6zev", "woe:centroid": [9.30108, 45.07922], "geom:latitude": 45.07922, "geom:longitude": 9.30108, "geom:hash": "u0n87wkv6zev", "woe:latitude": 45.07922, "geom:centroid": [9.30108, 45.07922], "woe:longitude": 9.30108, "woe:repo": "woeplanet-poi-it", "geom:area": 0.0, "woe:scale": 19}}