{"type": "Feature", "id": 22311953, "properties": {"woe:id": 22311953, "woe:parent_id": 726488, "woe:name": "Stazione di Q. T. 8", "woe:placetype": 20, "woe:placetype_name": "POI", "woe:lang": "ITA", "iso:country": "IT", "meta:provider": ["geoplanet:7.3.1", "geoplanet:7.3.2", "geoplanet:7.4.0", "geoplanet:7.4.1", "geoplanet:7.5.1", "geoplanet:7.5.2", "geoplanet:7.6.0", "geoplanet:7.8.1", "geoplanet:7.9.0", "geoplanet:7.10.0", "geoplanet:8.0.0", "woeplanet:8.0.0"], "meta:indexed": "2020-08-20T20:20:39.267090", "woe:alias_ITA_V": ["Stazione Q. T. 8"], "meta:updated": "2020-08-22T02:30:24.396141", "woe:hierarchy": {"continent": 24865675, "country": 23424853, "town": 0, "planet": 1, "county": 12591813, "suburb": 0, "state": 7153338, "region": 0, "localadmin": 12675801}, "woe:timezone_id": 28350914, "woe:hash": "u0n6zbmpu6cy", "woe:centroid": [9.13669, 45.486118], "geom:latitude": 45.486118, "geom:longitude": 9.13669, "geom:hash": "u0n6zbmpu6cy", "woe:latitude": 45.486118, "geom:centroid": [9.13669, 45.486118], "woe:longitude": 9.13669, "woe:repo": "woeplanet-poi-it"}, "geometry": {"coordinates": [9.13669, 45.486118], "type": "Point"}}