{"type": "Feature", "id": 22561647, "geometry": {"type": "Point", "coordinates": [8.61918, 45.908508]}, "properties": {"woe:id": 22561647, "woe:parent_id": 717088, "woe:name": "Stazione di Laveno Mombello Nord", "woe:placetype": 20, "woe:placetype_name": "POI", "woe:lang": "ITA", "iso:country": "IT", "meta:provider": ["geoplanet:7.3.1", "geoplanet:7.3.2", "geoplanet:7.4.0", "geoplanet:7.4.1", "geoplanet:7.5.1", "geoplanet:7.5.2", "geoplanet:7.6.0", "geoplanet:7.8.1", "geoplanet:7.9.0", "geoplanet:7.10.0", "geoplanet:8.0.0", "woeplanet:8.0.0"], "meta:indexed": "2020-08-20T20:20:39.622632", "woe:alias_ITA_V": ["Stazione Ferroviaria di Laveno Mombello Fnm", "Stazione Laveno Mombello Fnm", "Stazione di Laveno Mombello Fnm", "Stazione Ferroviaria Laveno Mombello Fnm", "Stazione Laveno Mombello Nord", "Stazione Ferroviaria di Laveno Mombello Nord", "Stazione Ferroviaria Laveno Mombello Nord"], "meta:updated": "2020-10-14T11:50:13.236927", "woe:hierarchy": {"continent": 24865675, "country": 23424853, "town": 0, "planet": 1, "county": 12591884, "suburb": 0, "state": 7153338, "region": 0, "localadmin": 12678536}, "woe:timezone_id": 28350914, "woe:hash": "u0njhjkk3qnm", "woe:centroid": [8.61918, 45.908508], "geom:latitude": 45.908508, "geom:longitude": 8.61918, "geom:hash": "u0njhjkk3qnm", "woe:latitude": 45.908508, "geom:centroid": [8.61918, 45.908508], "woe:longitude": 8.61918, "woe:repo": "woeplanet-poi-it", "geom:area": 0.0, "woe:scale": 19}}