{"type": "Feature", "id": 22314439, "properties": {"woe:id": 22314439, "woe:parent_id": 723406, "woe:name": "Stazione di Apice-Sant'arcangelo Trimonte-Bonito", "woe:placetype": 20, "woe:placetype_name": "POI", "woe:lang": "ITA", "iso:country": "IT", "meta:provider": ["geoplanet:7.3.1", "geoplanet:7.3.2", "geoplanet:7.4.0", "geoplanet:7.4.1", "geoplanet:7.5.1", "geoplanet:7.5.2", "geoplanet:7.6.0", "geoplanet:7.8.1", "geoplanet:7.9.0", "geoplanet:7.10.0", "geoplanet:8.0.0", "woeplanet:8.0.0"], "meta:indexed": "2020-08-20T20:20:39.326785", "woe:alias_ITA_V": ["Stazione Apice-Sant'arcangelo-Bonito", "Stazione di Apice-Sant'arcangelo-Bonito", "Stazione Ferroviaria di Apice-Sant'arcangelo-Bonito", "Stazione Ferroviaria Apice-Sant'arcangelo-Bonito", "Stazione Apice-Sant'arcangelo Trimonte-Bonito", "Stazione Ferroviaria di Apice-Sant'arcangelo Trimonte-Bonito", "Stazione Ferroviaria Apice-Sant'arcangelo Trimonte-Bonito"], "meta:updated": "2020-08-22T02:30:24.425199", "woe:hierarchy": {"continent": 24865675, "country": 23424853, "town": 0, "planet": 1, "county": 12591877, "suburb": 0, "state": 7153333, "region": 0, "localadmin": 12680868}, "woe:timezone_id": 28350914, "woe:hash": "sr6d53rw33r4", "woe:centroid": [14.91881, 41.140759], "geom:latitude": 41.140759, "geom:longitude": 14.91881, "geom:hash": "sr6d53rw33r4", "woe:latitude": 41.140759, "geom:centroid": [14.91881, 41.140759], "woe:longitude": 14.91881, "woe:repo": "woeplanet-poi-it"}, "geometry": {"coordinates": [14.91881, 41.140759], "type": "Point"}}