{"type": "Feature", "id": 22568485, "geometry": {"type": "Point", "coordinates": [9.1211, 45.503849]}, "properties": {"woe:id": 22568485, "woe:parent_id": 20150331, "woe:name": "Cimitero Maggiore", "woe:placetype": 20, "woe:placetype_name": "POI", "woe:lang": "ITA", "iso:country": "IT", "meta:provider": ["geoplanet:7.3.1", "geoplanet:7.3.2", "geoplanet:7.4.0", "geoplanet:7.4.1", "geoplanet:7.5.1", "geoplanet:7.5.2", "geoplanet:7.6.0", "geoplanet:7.8.1", "geoplanet:7.9.0", "geoplanet:7.10.0", "geoplanet:8.0.0", "woeplanet:8.0.0"], "meta:indexed": "2020-08-20T20:20:39.648455", "meta:updated": "2020-10-14T11:50:13.289480", "woe:hierarchy": {"continent": 24865675, "country": 23424853, "town": 0, "planet": 1, "county": 12591813, "suburb": 0, "state": 7153338, "region": 0, "localadmin": 12675801}, "woe:timezone_id": 28350914, "woe:hash": "u0n6ze9z1h30", "woe:centroid": [9.1211, 45.503849], "geom:latitude": 45.503849, "geom:longitude": 9.1211, "geom:hash": "u0n6ze9z1h30", "woe:latitude": 45.503849, "geom:centroid": [9.1211, 45.503849], "woe:longitude": 9.1211, "woe:repo": "woeplanet-poi-it", "geom:area": 0.0, "woe:scale": 19}}