{"type": "Feature", "id": 22319186, "properties": {"woe:id": 22319186, "woe:parent_id": 722697, "woe:name": "Stazione di Reggio Calabria San Gregorio", "woe:placetype": 20, "woe:placetype_name": "POI", "woe:lang": "ITA", "iso:country": "IT", "meta:provider": ["geoplanet:7.3.1", "geoplanet:7.3.2", "geoplanet:7.4.0", "geoplanet:7.4.1", "geoplanet:7.5.1", "geoplanet:7.5.2", "geoplanet:7.6.0", "geoplanet:7.8.1", "geoplanet:7.9.0", "geoplanet:7.10.0", "geoplanet:8.0.0", "woeplanet:8.0.0"], "meta:indexed": "2020-08-20T20:20:39.452727", "woe:alias_ITA_V": ["Stazione Reggio Calabria San Gregorio", "Stazione Ferroviaria di Reggio Calabria San Gregorio", "Stazione Ferroviaria Reggio Calabria San Gregorio"], "meta:updated": "2020-08-22T02:30:24.475111", "woe:hierarchy": {"continent": 24865675, "country": 23424853, "town": 0, "planet": 1, "county": 12591831, "suburb": 0, "state": 7153332, "region": 0, "localadmin": 12676175}, "woe:timezone_id": 28350914, "woe:hash": "sqg0s0ku5tsj", "woe:centroid": [15.65121, 38.058731], "geom:latitude": 38.058731, "geom:longitude": 15.65121, "geom:hash": "sqg0s0ku5tsj", "woe:latitude": 38.058731, "geom:centroid": [15.65121, 38.058731], "woe:longitude": 15.65121, "woe:repo": "woeplanet-poi-it"}, "geometry": {"coordinates": [15.65121, 38.058731], "type": "Point"}}