{"type": "Feature", "id": 22639401, "properties": {"woe:id": 22639401, "woe:parent_id": 726449, "woe:name": "Catacombe di Priscilla", "woe:placetype": 20, "woe:placetype_name": "POI", "woe:lang": "ITA", "iso:country": "IT", "meta:provider": ["geoplanet:7.3.1", "geoplanet:7.3.2", "geoplanet:7.4.0", "geoplanet:7.4.1", "geoplanet:7.5.1", "geoplanet:7.5.2", "geoplanet:7.6.0", "geoplanet:7.8.1", "geoplanet:7.9.0", "geoplanet:7.10.0", "geoplanet:8.0.0", "woeplanet:8.0.0"], "meta:indexed": "2020-08-20T20:20:40.005906", "meta:updated": "2020-08-22T02:30:24.705111", "woe:hierarchy": {"continent": 24865675, "country": 23424853, "town": 0, "planet": 1, "county": 12591802, "suburb": 0, "state": 7153336, "region": 0, "localadmin": 12675698}, "woe:timezone_id": 28350914, "woe:hash": "sr2ys9he1hhr", "woe:centroid": [12.50867, 41.929859], "geom:latitude": 41.929859, "geom:longitude": 12.50867, "geom:hash": "sr2ys9he1hhr", "woe:latitude": 41.929859, "geom:centroid": [12.50867, 41.929859], "woe:longitude": 12.50867, "woe:repo": "woeplanet-poi-it"}, "geometry": {"coordinates": [12.50867, 41.929859], "type": "Point"}}