{"type": "Feature", "id": 22648731, "properties": {"woe:id": 22648731, "woe:parent_id": 719258, "woe:name": "Villa Pignatelli", "woe:placetype": 20, "woe:placetype_name": "POI", "woe:lang": "ITA", "iso:country": "IT", "meta:provider": ["geoplanet:7.3.1", "geoplanet:7.3.2", "geoplanet:7.4.0", "geoplanet:7.4.1", "geoplanet:7.5.1", "geoplanet:7.5.2", "geoplanet:7.6.0", "geoplanet:7.8.1", "geoplanet:7.9.0", "geoplanet:7.10.0", "geoplanet:8.0.0", "woeplanet:8.0.0"], "meta:indexed": "2020-08-20T20:20:40.033331", "meta:updated": "2020-08-22T02:30:24.717186", "woe:hierarchy": {"continent": 24865675, "country": 23424853, "town": 0, "planet": 1, "county": 12591829, "suburb": 0, "state": 7153333, "region": 0, "localadmin": 20076932}, "woe:timezone_id": 28350914, "woe:hash": "sr607ct43779", "woe:centroid": [14.23422, 40.833839], "geom:latitude": 40.833839, "geom:longitude": 14.23422, "geom:hash": "sr607ct43779", "woe:latitude": 40.833839, "geom:centroid": [14.23422, 40.833839], "woe:longitude": 14.23422, "woe:repo": "woeplanet-poi-it"}, "geometry": {"coordinates": [14.23422, 40.833839], "type": "Point"}}