{"type": "Feature", "id": 22319865, "geometry": {"type": "Point", "coordinates": [9.20324, 45.646179]}, "properties": {"woe:id": 22319865, "woe:parent_id": 724049, "woe:name": "Stazione di Seregno", "woe:placetype": 20, "woe:placetype_name": "POI", "woe:lang": "ITA", "iso:country": "IT", "meta:provider": ["geoplanet:7.3.1", "geoplanet:7.3.2", "geoplanet:7.4.0", "geoplanet:7.4.1", "geoplanet:7.5.1", "geoplanet:7.5.2", "geoplanet:7.6.0", "geoplanet:7.8.1", "geoplanet:7.9.0", "geoplanet:7.10.0", "geoplanet:8.0.0", "woeplanet:8.0.0"], "meta:indexed": "2020-08-20T20:20:39.482479", "woe:alias_ITA_V": ["Stazione Seregno", "Stazione Ferroviaria di Seregno", "Stazione Ferroviaria Seregno"], "meta:updated": "2020-10-14T11:50:14.181771", "woe:hierarchy": {"continent": 24865675, "country": 23424853, "town": 0, "planet": 1, "county": 56043515, "suburb": 0, "state": 7153338, "region": 0, "localadmin": 12681963}, "woe:timezone_id": 28350914, "woe:hash": "u0ne9mts703p", "woe:centroid": [9.20324, 45.646179], "geom:latitude": 45.646179, "geom:longitude": 9.20324, "geom:hash": "u0ne9mts703p", "woe:latitude": 45.646179, "geom:centroid": [9.20324, 45.646179], "woe:longitude": 9.20324, "woe:repo": "woeplanet-poi-it", "geom:area": 0.0, "woe:scale": 19}}