{"type": "Feature", "id": 23050499, "geometry": {"type": "Point", "coordinates": [7.60676, 44.997421]}, "properties": {"woe:id": 23050499, "woe:parent_id": 12680674, "woe:name": "Museo di Storia E Arte Ed Ammobiliamento-Palazzinadi Caccia Stupinigi", "woe:placetype": 20, "woe:placetype_name": "POI", "woe:lang": "ITA", "iso:country": "IT", "meta:provider": ["geoplanet:7.3.1", "geoplanet:7.3.2", "geoplanet:7.4.0", "geoplanet:7.4.1", "geoplanet:7.5.1", "geoplanet:7.5.2", "geoplanet:7.6.0", "geoplanet:7.8.1", "geoplanet:7.9.0", "geoplanet:7.10.0", "geoplanet:8.0.0", "woeplanet:8.0.0"], "meta:indexed": "2020-08-20T20:20:40.062886", "meta:updated": "2020-10-14T11:50:13.219714", "woe:hierarchy": {"continent": 24865675, "country": 23424853, "town": 0, "planet": 1, "county": 12591807, "suburb": 0, "state": 7153341, "region": 0, "localadmin": 12680674}, "woe:timezone_id": 28350914, "woe:hash": "spvrvpe0fr5r", "woe:centroid": [7.60676, 44.997421], "geom:latitude": 44.997421, "geom:longitude": 7.60676, "geom:hash": "spvrvpe0fr5r", "woe:latitude": 44.997421, "geom:centroid": [7.60676, 44.997421], "woe:longitude": 7.60676, "woe:repo": "woeplanet-poi-it", "geom:area": 0.0, "woe:scale": 19}}