{"type": "Feature", "id": 22310434, "properties": {"woe:id": 22310434, "woe:parent_id": 29336706, "woe:name": "Stazione di Ardenza", "woe:placetype": 20, "woe:placetype_name": "POI", "woe:lang": "ITA", "iso:country": "IT", "meta:provider": ["geoplanet:7.3.1", "geoplanet:7.3.2", "geoplanet:7.4.0", "geoplanet:7.4.1", "geoplanet:7.5.1", "geoplanet:7.5.2", "geoplanet:7.6.0", "geoplanet:7.8.1", "geoplanet:7.9.0", "geoplanet:7.10.0", "geoplanet:8.0.0", "woeplanet:8.0.0"], "meta:indexed": "2020-08-20T20:20:39.204899", "woe:alias_ITA_V": ["Stazione di Livorno Ardenza", "Stazione Ferroviaria Livorno Ardenza", "Stazione Ferroviaria di Livorno Ardenza", "Stazione Livorno Ardenza", "Stazione Ardenza", "Stazione Ferroviaria di Ardenza", "Stazione Ferroviaria Ardenza"], "meta:updated": "2020-08-22T02:30:24.364837", "woe:hierarchy": {"continent": 24865675, "country": 23424853, "town": 0, "planet": 1, "county": 12591891, "suburb": 0, "state": 7153345, "region": 0, "localadmin": 12676124}, "woe:timezone_id": 28350914, "woe:hash": "spxre43sh0xk", "woe:centroid": [10.32939, 43.518909], "geom:latitude": 43.518909, "geom:longitude": 10.32939, "geom:hash": "spxre43sh0xk", "woe:latitude": 43.518909, "geom:centroid": [10.32939, 43.518909], "woe:longitude": 10.32939, "woe:repo": "woeplanet-poi-it"}, "geometry": {"coordinates": [10.32939, 43.518909], "type": "Point"}}