{"type": "Feature", "id": 29229290, "properties": {"woe:id": 29229290, "woe:parent_id": 721943, "woe:name": "Campo de' Fiori", "woe:placetype": 20, "woe:placetype_name": "POI", "woe:lang": "ITA", "iso:country": "IT", "meta:provider": ["geoplanet:7.3.1", "geoplanet:7.3.2", "geoplanet:7.4.0", "geoplanet:7.4.1", "geoplanet:7.5.1", "geoplanet:7.5.2", "geoplanet:7.6.0", "geoplanet:7.8.1", "geoplanet:7.9.0", "geoplanet:7.10.0", "geoplanet:8.0.0", "woeplanet:8.0.0"], "meta:indexed": "2020-08-20T20:20:40.559618", "woe:alias_ENG_V": ["Campodeifiori"], "woe:alias_ITA_V": ["Piazza Campo de' Fiori", "Campodefiori"], "woe:alias_ENG_P": ["Campo dei Fiori"], "meta:updated": "2020-08-22T02:30:24.942053", "woe:alias_POR_Q": ["Campo del Fiori"], "woe:hierarchy": {"continent": 24865675, "country": 23424853, "town": 0, "planet": 1, "county": 12591802, "suburb": 0, "state": 7153336, "region": 0, "localadmin": 12675698}, "woe:timezone_id": 28350914, "woe:hash": "sr2y7fcu2z9x", "woe:centroid": [12.47192, 41.89576], "geom:latitude": 41.89576, "geom:longitude": 12.47192, "geom:hash": "sr2y7fcu2z9x", "woe:latitude": 41.89576, "geom:centroid": [12.47192, 41.89576], "woe:longitude": 12.47192, "woe:repo": "woeplanet-poi-it"}, "geometry": {"coordinates": [12.47192, 41.89576], "type": "Point"}}