{"type": "Feature", "id": 22306510, "properties": {"woe:id": 22306510, "woe:parent_id": 712326, "woe:name": "Stazione di Carpignano Sesia", "woe:placetype": 20, "woe:placetype_name": "POI", "woe:lang": "ITA", "iso:country": "IT", "meta:provider": ["geoplanet:7.3.1", "geoplanet:7.3.2", "geoplanet:7.4.0", "geoplanet:7.4.1", "geoplanet:7.5.1", "geoplanet:7.5.2", "geoplanet:7.6.0", "geoplanet:7.8.1", "geoplanet:7.9.0", "geoplanet:7.10.0", "geoplanet:8.0.0", "woeplanet:8.0.0"], "meta:indexed": "2020-08-20T20:20:39.071584", "woe:alias_ITA_V": ["Stazione Carpignano Sesia", "Stazione Ferroviaria di Carpignano Sesia", "Stazione Ferroviaria Carpignano Sesia"], "meta:updated": "2020-08-22T02:30:24.271855", "woe:hierarchy": {"continent": 24865675, "country": 23424853, "town": 0, "planet": 1, "county": 12591859, "suburb": 0, "state": 7153341, "region": 0, "localadmin": 12677729}, "woe:timezone_id": 28350914, "woe:hash": "u0jgp8m6b04j", "woe:centroid": [8.42274, 45.52919], "geom:latitude": 45.52919, "geom:longitude": 8.42274, "geom:hash": "u0jgp8m6b04j", "woe:latitude": 45.52919, "geom:centroid": [8.42274, 45.52919], "woe:longitude": 8.42274, "woe:repo": "woeplanet-poi-it"}, "geometry": {"coordinates": [8.42274, 45.52919], "type": "Point"}}