{"type": "Feature", "id": 22590569, "geometry": {"type": "Point", "coordinates": [11.28258, 45.357731]}, "properties": {"woe:id": 22590569, "woe:parent_id": 710261, "woe:name": "Museo Napoleonico G. A. Antonelli", "woe:placetype": 20, "woe:placetype_name": "POI", "woe:lang": "ITA", "iso:country": "IT", "meta:provider": ["geoplanet:7.3.1", "geoplanet:7.3.2", "geoplanet:7.4.0", "geoplanet:7.4.1", "geoplanet:7.5.1", "geoplanet:7.5.2", "geoplanet:7.6.0", "geoplanet:7.8.1", "geoplanet:7.9.0", "geoplanet:7.10.0", "geoplanet:8.0.0", "woeplanet:8.0.0"], "meta:indexed": "2020-08-20T20:20:39.748043", "meta:updated": "2020-10-14T11:50:13.366609", "woe:hierarchy": {"continent": 24865675, "country": 23424853, "town": 0, "planet": 1, "county": 12591857, "suburb": 0, "state": 7153349, "region": 0, "localadmin": 12682527}, "woe:timezone_id": 28350914, "woe:hash": "u20409pezjvk", "woe:centroid": [11.28258, 45.357731], "geom:latitude": 45.357731, "geom:longitude": 11.28258, "geom:hash": "u20409pezjvk", "woe:latitude": 45.357731, "geom:centroid": [11.28258, 45.357731], "woe:longitude": 11.28258, "woe:repo": "woeplanet-poi-it", "geom:area": 0.0, "woe:scale": 19}}