{"type": "Feature", "id": 23070236, "geometry": {"type": "Point", "coordinates": [9.23551, 45.606232]}, "properties": {"woe:id": 23070236, "woe:parent_id": 717335, "woe:name": "Stazione di Lissone-Muggi\u00f2", "woe:placetype": 20, "woe:placetype_name": "POI", "woe:lang": "ITA", "iso:country": "IT", "meta:provider": ["geoplanet:7.3.1", "geoplanet:7.3.2", "geoplanet:7.4.0", "geoplanet:7.4.1", "geoplanet:7.5.1", "geoplanet:7.5.2", "geoplanet:7.6.0", "geoplanet:7.8.1", "geoplanet:7.9.0", "geoplanet:7.10.0", "geoplanet:8.0.0", "woeplanet:8.0.0"], "meta:indexed": "2020-08-20T20:20:40.162295", "woe:alias_ITA_V": ["Stazione Lissone-Muggi\u00f2", "Stazione Ferroviaria di Lissone-Muggi\u00f2", "Stazione Ferroviaria Lissone-Muggi\u00f2"], "meta:updated": "2020-10-14T11:50:13.099220", "woe:alias_ITA_S": ["Stazione Ferroviaria di Lissone-Muggio", "Stazione di Lissone-Muggio", "Stazione Ferroviaria Lissone-Muggio", "Stazione Lissone-Muggio"], "woe:hierarchy": {"continent": 24865675, "country": 23424853, "town": 0, "planet": 1, "county": 56043515, "suburb": 0, "state": 7153338, "region": 0, "localadmin": 12679978}, "woe:timezone_id": 28350914, "woe:hash": "u0ne6nm5dcz6", "woe:centroid": [9.23551, 45.606232], "geom:latitude": 45.606232, "geom:longitude": 9.23551, "geom:hash": "u0ne6nm5dcz6", "woe:latitude": 45.606232, "geom:centroid": [9.23551, 45.606232], "woe:longitude": 9.23551, "woe:repo": "woeplanet-poi-it", "geom:area": 0.0, "woe:scale": 19}}