{"type": "Feature", "id": 23114854, "geometry": {"type": "Point", "coordinates": [13.51114, 43.62088]}, "properties": {"woe:id": 23114854, "woe:parent_id": 710129, "woe:name": "Palazzo Bosdari", "woe:placetype": 20, "woe:placetype_name": "POI", "woe:lang": "ITA", "iso:country": "IT", "meta:provider": ["geoplanet:7.3.1", "geoplanet:7.3.2", "geoplanet:7.4.0", "geoplanet:7.4.1", "geoplanet:7.5.1", "geoplanet:7.5.2", "geoplanet:7.6.0", "geoplanet:7.8.1", "geoplanet:7.9.0", "geoplanet:7.10.0", "geoplanet:8.0.0", "woeplanet:8.0.0"], "meta:indexed": "2020-08-20T20:20:40.276995", "meta:updated": "2020-10-14T11:50:14.649816", "woe:hierarchy": {"continent": 24865675, "country": 23424853, "town": 0, "planet": 1, "county": 12591847, "suburb": 0, "state": 7153339, "region": 0, "localadmin": 12676073}, "woe:timezone_id": 28350914, "woe:hash": "src85kyw03kh", "woe:centroid": [13.51114, 43.62088], "geom:latitude": 43.62088, "geom:longitude": 13.51114, "geom:hash": "src85kyw03kh", "woe:latitude": 43.62088, "geom:centroid": [13.51114, 43.62088], "woe:longitude": 13.51114, "woe:repo": "woeplanet-poi-it", "geom:area": 0.0, "woe:scale": 19}}