{"type": "Feature", "id": 23114503, "properties": {"woe:id": 23114503, "woe:parent_id": 722712, "woe:name": "Musei Della Citt\u00e0-Museo d'Arte Sacra e Pinacoteca", "woe:placetype": 20, "woe:placetype_name": "POI", "woe:lang": "ITA", "iso:country": "IT", "meta:provider": ["geoplanet:7.3.1", "geoplanet:7.3.2", "geoplanet:7.4.0", "geoplanet:7.4.1", "geoplanet:7.5.1", "geoplanet:7.5.2", "geoplanet:7.6.0", "geoplanet:7.8.1", "geoplanet:7.9.0", "geoplanet:7.10.0", "geoplanet:8.0.0", "woeplanet:8.0.0"], "meta:indexed": "2020-08-20T20:20:40.274033", "meta:updated": "2020-08-22T02:30:24.827282", "woe:alias_ITA_S": ["Musei Della Citta-Museo d'Arte Sacra e Pinacoteca"], "woe:hierarchy": {"continent": 24865675, "country": 23424853, "town": 0, "planet": 1, "county": 12591841, "suburb": 0, "state": 7153339, "region": 0, "localadmin": 12677567}, "woe:timezone_id": 28350914, "woe:hash": "srbc8zhhfp7k", "woe:centroid": [12.34323, 43.896729], "geom:latitude": 43.896729, "geom:longitude": 12.34323, "geom:hash": "srbc8zhhfp7k", "woe:latitude": 43.896729, "geom:centroid": [12.34323, 43.896729], "woe:longitude": 12.34323, "woe:repo": "woeplanet-poi-it"}, "geometry": {"coordinates": [12.34323, 43.896729], "type": "Point"}}