{"type": "Feature", "id": 22303949, "geometry": {"type": "Point", "coordinates": [13.52286, 43.575062]}, "properties": {"woe:id": 22303949, "woe:parent_id": 29339009, "woe:name": "Stazione di Varano", "woe:placetype": 20, "woe:placetype_name": "POI", "woe:lang": "ITA", "iso:country": "IT", "meta:provider": ["geoplanet:7.3.1", "geoplanet:7.3.2", "geoplanet:7.4.0", "geoplanet:7.4.1", "geoplanet:7.5.1", "geoplanet:7.5.2", "geoplanet:7.6.0", "geoplanet:7.8.1", "geoplanet:7.9.0", "geoplanet:7.10.0", "geoplanet:8.0.0", "woeplanet:8.0.0"], "meta:indexed": "2020-08-20T20:20:38.999042", "woe:alias_ITA_V": ["Stazione Varano", "Stazione Ferroviaria di Varano", "Stazione Ferroviaria Varano"], "meta:updated": "2020-10-14T11:50:13.791727", "woe:hierarchy": {"continent": 24865675, "country": 23424853, "town": 0, "planet": 1, "county": 12591847, "suburb": 0, "state": 7153339, "region": 0, "localadmin": 12676073}, "woe:timezone_id": 28350914, "woe:hash": "sr9xgsx51kr3", "woe:centroid": [13.52286, 43.575062], "geom:latitude": 43.575062, "geom:longitude": 13.52286, "geom:hash": "sr9xgsx51kr3", "woe:latitude": 43.575062, "geom:centroid": [13.52286, 43.575062], "woe:longitude": 13.52286, "woe:repo": "woeplanet-poi-it", "geom:area": 0.0, "woe:scale": 19}}