{"type": "Feature", "id": 23116281, "geometry": {"type": "Point", "coordinates": [13.43731, 43.30703]}, "properties": {"woe:id": 23116281, "woe:parent_id": 20132494, "woe:name": "Stadio Helvia Recina", "woe:placetype": 20, "woe:placetype_name": "POI", "woe:lang": "ITA", "iso:country": "IT", "meta:provider": ["geoplanet:7.3.1", "geoplanet:7.3.2", "geoplanet:7.4.0", "geoplanet:7.4.1", "geoplanet:7.5.1", "geoplanet:7.5.2", "geoplanet:7.6.0", "geoplanet:7.8.1", "geoplanet:7.9.0", "geoplanet:7.10.0", "geoplanet:8.0.0", "woeplanet:8.0.0"], "meta:indexed": "2020-08-20T20:20:40.283846", "meta:updated": "2020-10-14T11:50:14.591515", "woe:hierarchy": {"continent": 24865675, "country": 23424853, "town": 0, "planet": 1, "county": 12591806, "suburb": 0, "state": 7153339, "region": 0, "localadmin": 12675712}, "woe:timezone_id": 28350914, "woe:hash": "sr9w3gbc8p88", "woe:centroid": [13.43731, 43.30703], "geom:latitude": 43.30703, "geom:longitude": 13.43731, "geom:hash": "sr9w3gbc8p88", "woe:latitude": 43.30703, "geom:centroid": [13.43731, 43.30703], "woe:longitude": 13.43731, "woe:repo": "woeplanet-poi-it", "geom:area": 0.0, "woe:scale": 19}}