{"type": "Feature", "id": 23138492, "properties": {"woe:id": 23138492, "woe:parent_id": 20148549, "woe:name": "Stazione di Castellalto-Canzano", "woe:placetype": 20, "woe:placetype_name": "POI", "woe:lang": "ITA", "iso:country": "IT", "meta:provider": ["geoplanet:7.3.1", "geoplanet:7.3.2", "geoplanet:7.4.0", "geoplanet:7.4.1", "geoplanet:7.5.1", "geoplanet:7.5.2", "geoplanet:7.6.0", "geoplanet:7.8.1", "geoplanet:7.9.0", "geoplanet:7.10.0", "geoplanet:8.0.0", "woeplanet:8.0.0"], "meta:indexed": "2020-08-20T20:20:40.383591", "woe:alias_ITA_V": ["Stazione Castellalto-Canzano", "Stazione Ferroviaria di Castellalto-Canzano", "Stazione Ferroviaria Castellalto-Canzano"], "meta:updated": "2020-08-22T02:30:24.879202", "woe:hierarchy": {"continent": 24865675, "country": 23424853, "town": 0, "planet": 1, "county": 12591815, "suburb": 0, "state": 7153350, "region": 0, "localadmin": 12676370}, "woe:timezone_id": 28350914, "woe:hash": "sr9fcue8yxfj", "woe:centroid": [13.79293, 42.695789], "geom:latitude": 42.695789, "geom:longitude": 13.79293, "geom:hash": "sr9fcue8yxfj", "woe:latitude": 42.695789, "geom:centroid": [13.79293, 42.695789], "woe:longitude": 13.79293, "woe:repo": "woeplanet-poi-it"}, "geometry": {"coordinates": [13.79293, 42.695789], "type": "Point"}}