{"type": "Feature", "id": 23068751, "geometry": {"type": "Point", "coordinates": [9.45846, 46.202648]}, "properties": {"woe:id": 23068751, "woe:parent_id": 29335636, "woe:name": "Stazione di Verceia", "woe:placetype": 20, "woe:placetype_name": "POI", "woe:lang": "ITA", "iso:country": "IT", "meta:provider": ["geoplanet:7.3.1", "geoplanet:7.3.2", "geoplanet:7.4.0", "geoplanet:7.4.1", "geoplanet:7.5.1", "geoplanet:7.5.2", "geoplanet:7.6.0", "geoplanet:7.8.1", "geoplanet:7.9.0", "geoplanet:7.10.0", "geoplanet:8.0.0", "woeplanet:8.0.0"], "meta:indexed": "2020-08-20T20:20:40.158108", "woe:alias_ITA_V": ["Stazione Verceia", "Stazione Ferroviaria di Verceia", "Stazione Ferroviaria Verceia"], "meta:updated": "2020-10-14T11:50:13.103094", "woe:hierarchy": {"continent": 24865675, "country": 23424853, "town": 0, "planet": 1, "county": 12591881, "suburb": 0, "state": 7153338, "region": 0, "localadmin": 12679404}, "woe:timezone_id": 28350914, "woe:hash": "u0nwz4zmyjff", "woe:centroid": [9.45846, 46.202648], "geom:latitude": 46.202648, "geom:longitude": 9.45846, "geom:hash": "u0nwz4zmyjff", "woe:latitude": 46.202648, "geom:centroid": [9.45846, 46.202648], "woe:longitude": 9.45846, "woe:repo": "woeplanet-poi-it", "geom:area": 0.0, "woe:scale": 19}}